{"metadata": {"dataVersion": "2", "matchId": "NA1_5222413435", "participants": ["UIzmaeHNqCVz8Eo3JKo9cbS0y9LimpVPCx88vSAYgh_9U_rP1he_TyPjCGlZbsDDGhDfAWUImfjFSg", "pIuKqcrPeaY9D6Vtnqsp2sdIS59C6YiYaqwXvbCHMBmCXc1vePWcrxSUYhals7YJ0VohdYjES68--A", "Q7x_1N1S0SGqvelbZVYpV2Py6b7Oa16BoMnCsk_ozv7SuHMCxgYmWvyWRv2C_Pit1X6sCf38aS_yTw", "K2-lKPBNbJoGtnTOi47zVmAbv8XnHxUOwYUIPLeFMIOVRA1AVFnUXIHr4DoVoPUobsYMNYn3CN5i7g", "Fkn8VJYa2kbHJOyRVQOQNayOG4uIbnUvKWucwpEM7RYYWvsAnvCO5VcaIL5lnyW-G2CanV8XjCz8Sw", "_6ZrpSOpHysz_IStR7shXbSV_1cCQN28AlvCS2kgLznZD8O7BF_N8-6sj6oPffc_FUugjwgcydh_zA", "HTqP5dug7zi1i0lGtmExmHZNmhpIgHNRDsMS1h5NE74E2jrzER-GzGx7n4KPD_eqFXN33OnkrKrfiQ", "9iX3byb9GA3veD_B7cEyB509TAE_y4AHTNoStg0-TPebVJ5Yyyqaa-fzgFnASU179PTWqkkcrAtpEg", "24ZsDGG_0A6h2-a8o3O-u6_vbsRtLA0XPhYDXTInzIxfdOI8TIxt1KjTHjLahbJ-QeZxAoZlORO2xg", "DMNamjYDDtuA5lsPIn2jB610zoD4He7IhKBQ-UqLdGgqO_w5lhHyv7BHJfd4Kn5sHWL2FHalRYaqIw"]}, "info": {"endOfGameResult": "GameComplete", "gameCreation": 1738704871277, "gameDuration": 1646, "gameEndTimestamp": 1738706591060, "gameId": 5222413435, "gameMode": "CLASSIC", "gameName": "teambuilder-match-5222413435", "gameStartTimestamp": 1738704945271, "gameType": "MATCHED_GAME", "gameVersion": "15.2.652.1536", "mapId": 11, "participants": [{"PlayerScore0": 0, "PlayerScore1": 0, "PlayerScore10": 0, "PlayerScore11": 0, "PlayerScore2": 0, "PlayerScore3": 0, "PlayerScore4": 0, "PlayerScore5": 0, "PlayerScore6": 0, "PlayerScore7": 0, "PlayerScore8": 0, "PlayerScore9": 0, "allInPings": 0, "assistMePings": 1, "assists": 3, "baronKills": 0, "basicPings": 0, "bountyLevel": 5, "challenges": {"12AssistStreakCount": 0, "HealFromMapSources": 1354.9320373535156, "InfernalScalePickup": 0, "SWARM_DefeatAatrox": 0, "SWARM_DefeatBriar": 0, "SWARM_DefeatMiniBosses": 0, "SWARM_EvolveWeapon": 0, "SWARM_Have3Passives": 0, "SWARM_KillEnemy": 0, "SWARM_PickupGold": 0, "SWARM_ReachLevel50": 0, "SWARM_Survive15Min": 0, "SWARM_WinWith5EvolvedWeapons": 0, "abilityUses": 233, "acesBefore15Minutes": 0, "alliedJungleMonsterKills": 0, "baronBuffGoldAdvantageOverThreshold": 1, "baronTakedowns": 1, "blastConeOppositeOpponentCount": 0, "bountyGold": 0, "buffsStolen": 0, "completeSupportQuestInTime": 0, "controlWardsPlaced": 0, "damagePerMinute": 581.2401225149758, "damageTakenOnTeamPercentage": 0.24122732532210897, "dancedWithRiftHerald": 0, "deathsByEnemyChamps": 0, "dodgeSkillShotsSmallWindow": 15, "doubleAces": 0, "dragonTakedowns": 1, "earliestBaron": 1562.687085109, "earliestDragonTakedown": 1389.4459262550001, "earlyLaningPhaseGoldExpAdvantage": 0, "effectiveHealAndShielding": 0, "elderDragonKillsWithOpposingSoul": 0, "elderDragonMultikills": 0, "enemyChampionImmobilizations": 0, "enemyJungleMonsterKills": 0, "epicMonsterKillsNearEnemyJungler": 0, "epicMonsterKillsWithin30SecondsOfSpawn": 1, "epicMonsterSteals": 0, "epicMonsterStolenWithoutSmite": 0, "firstTurretKilled": 1, "firstTurretKilledTime": 894.243710104, "fistBumpParticipation": 3, "flawlessAces": 0, "fullTeamTakedown": 1, "gameLength": 1646.3477353120002, "getTakedownsInAllLanesEarlyJungleAsLaner": 0, "goldPerMinute": 361.40536624678595, "hadOpenNexus": 0, "immobilizeAndKillWithAlly": 0, "initialBuffCount": 0, "initialCrabCount": 0, "jungleCsBefore10Minutes": 0, "junglerTakedownsNearDamagedEpicMonster": 0, "kTurretsDestroyedBeforePlatesFall": 0, "kda": 8, "killAfterHiddenWithAlly": 2, "killParticipation": 0.22857142857142856, "killedChampTookFullTeamDamageSurvived": 0, "killingSprees": 1, "killsNearEnemyTurret": 1, "killsOnOtherLanesEarlyJungleAsLaner": 0, "killsOnRecentlyHealedByAramPack": 0, "killsUnderOwnTurret": 0, "killsWithHelpFromEpicMonster": 0, "knockEnemyIntoTeamAndKill": 0, "landSkillShotsEarlyGame": 0, "laneMinionsFirst10Minutes": 54, "laningPhaseGoldExpAdvantage": 0, "legendaryCount": 0, "legendaryItemUsed": [3078, 3110], "lostAnInhibitor": 0, "maxCsAdvantageOnLaneOpponent": 5.000000029802322, "maxKillDeficit": 2, "maxLevelLeadLaneOpponent": 3, "mejaisFullStackInTime": 0, "moreEnemyJungleThanOpponent": 0, "multiKillOneSpell": 0, "multiTurretRiftHeraldCount": 0, "multikills": 0, "multikillsAfterAggressiveFlash": 0, "outerTurretExecutesBefore10Minutes": 0, "outnumberedKills": 1, "outnumberedNexusKill": 0, "perfectDragonSoulsTaken": 1, "perfectGame": 0, "pickKillWithAlly": 6, "playedChampSelectPosition": 1, "poroExplosions": 0, "quickCleanse": 0, "quickFirstTurret": 0, "quickSoloKills": 0, "riftHeraldTakedowns": 0, "saveAllyFromDeath": 0, "scuttleCrabKills": 0, "skillshotsDodged": 97, "skillshotsHit": 0, "snowballsHit": 0, "soloBaronKills": 0, "soloKills": 2, "stealthWardsPlaced": 6, "survivedSingleDigitHpCount": 0, "survivedThreeImmobilizesInFight": 3, "takedownOnFirstTurret": 0, "takedowns": 8, "takedownsAfterGainingLevelAdvantage": 0, "takedownsBeforeJungleMinionSpawn": 0, "takedownsFirstXMinutes": 1, "takedownsInAlcove": 0, "takedownsInEnemyFountain": 0, "teamBaronKills": 1, "teamDamagePercentage": 0.1897672882424237, "teamElderDragonKills": 0, "teamRiftHeraldKills": 1, "tookLargeDamageSurvived": 0, "turretPlatesTaken": 0, "turretTakedowns": 4, "turretsTakenWithRiftHerald": 5, "twentyMinionsIn3SecondsCount": 0, "twoWardsOneSweeperCount": 0, "unseenRecalls": 0, "visionScoreAdvantageLaneOpponent": -0.010677933692932129, "visionScorePerMinute": 0.4663755867138856, "voidMonsterKill": 1, "wardTakedowns": 0, "wardTakedownsBefore20M": 0, "wardsGuarded": 0}, "champExperience": 15467, "champLevel": 16, "championId": 75, "championName": "Nasus", "championTransform": 0, "commandPings": 19, "consumablesPurchased": 2, "damageDealtToBuildings": 7085, "damageDealtToObjectives": 15556, "damageDealtToTurrets": 7085, "damageSelfMitigated": 25285, "dangerPings": 0, "deaths": 0, "detectorWardsPlaced": 0, "doubleKills": 0, "dragonKills": 1, "eligibleForProgression": true, "enemyMissingPings": 3, "enemyVisionPings": 0, "firstBloodAssist": false, "firstBloodKill": false, "firstTowerAssist": false, "firstTowerKill": false, "gameEndedInEarlySurrender": false, "gameEndedInSurrender": false, "getBackPings": 0, "goldEarned": 9916, "goldSpent": 7583, "holdPings": 0, "individualPosition": "TOP", "inhibitorKills": 1, "inhibitorTakedowns": 2, "inhibitorsLost": 0, "item0": 1054, "item1": 3078, "item2": 3047, "item3": 3110, "item4": 0, "item5": 0, "item6": 3340, "itemsPurchased": 12, "killingSprees": 1, "kills": 5, "lane": "TOP", "largestCriticalStrike": 0, "largestKillingSpree": 5, "largestMultiKill": 1, "longestTimeSpentLiving": 0, "magicDamageDealt": 10749, "magicDamageDealtToChampions": 2247, "magicDamageTaken": 6481, "missions": {"playerScore0": 0, "playerScore1": 0, "playerScore2": 0, "playerScore3": 0, "playerScore4": 0, "playerScore5": 0, "playerScore6": 0, "playerScore7": 0, "playerScore8": 0, "playerScore9": 0, "playerScore10": 0, "playerScore11": 0}, "needVisionPings": 0, "neutralMinionsKilled": 12, "nexusKills": 0, "nexusLost": 0, "nexusTakedowns": 1, "objectivesStolen": 0, "objectivesStolenAssists": 0, "onMyWayPings": 31, "participantId": 1, "pentaKills": 0, "perks": {"statPerks": {"defense": 5001, "flex": 5001, "offense": 5005}, "styles": [{"description": "primaryStyle", "selections": [{"perk": 8010, "var1": 311, "var2": 0, "var3": 0}, {"perk": 9111, "var1": 747, "var2": 160, "var3": 0}, {"perk": 9104, "var1": 21, "var2": 50, "var3": 0}, {"perk": 8014, "var1": 249, "var2": 0, "var3": 0}], "style": 8000}, {"description": "subStyle", "selections": [{"perk": 8446, "var1": 1219, "var2": 0, "var3": 0}, {"perk": 8473, "var1": 578, "var2": 0, "var3": 0}], "style": 8400}]}, "physicalDamageDealt": 124921, "physicalDamageDealtToChampions": 12837, "physicalDamageTaken": 18320, "placement": 0, "playerAugment1": 0, "playerAugment2": 0, "playerAugment3": 0, "playerAugment4": 0, "playerAugment5": 0, "playerAugment6": 0, "playerSubteamId": 0, "profileIcon": 6804, "pushPings": 0, "puuid": "UIzmaeHNqCVz8Eo3JKo9cbS0y9LimpVPCx88vSAYgh_9U_rP1he_TyPjCGlZbsDDGhDfAWUImfjFSg", "quadraKills": 0, "retreatPings": 0, "riotIdGameName": "abdallahFTW", "riotIdTagline": "NA1", "role": "SOLO", "sightWardsBoughtInGame": 0, "spell1Casts": 173, "spell2Casts": 20, "spell3Casts": 36, "spell4Casts": 4, "subteamPlacement": 0, "summoner1Casts": 4, "summoner1Id": 14, "summoner2Casts": 4, "summoner2Id": 4, "summonerId": "Z9BB0THMvukcpwhy5GXw1osWB-6RIg_K0LbyndI7ayEXpAqA", "summonerLevel": 167, "summonerName": "abdallahFTW", "teamEarlySurrendered": false, "teamId": 100, "teamPosition": "TOP", "timeCCingOthers": 12, "timePlayed": 1646, "totalAllyJungleMinionsKilled": 0, "totalDamageDealt": 137001, "totalDamageDealtToChampions": 15948, "totalDamageShieldedOnTeammates": 0, "totalDamageTaken": 26158, "totalEnemyJungleMinionsKilled": 0, "totalHeal": 16733, "totalHealsOnTeammates": 0, "totalMinionsKilled": 148, "totalTimeCCDealt": 134, "totalTimeSpentDead": 0, "totalUnitsHealed": 1, "tripleKills": 0, "trueDamageDealt": 1330, "trueDamageDealtToChampions": 864, "trueDamageTaken": 1356, "turretKills": 1, "turretTakedowns": 4, "turretsLost": 4, "unrealKills": 0, "visionClearedPings": 0, "visionScore": 12, "visionWardsBoughtInGame": 0, "wardsKilled": 0, "wardsPlaced": 6, "win": true}, {"PlayerScore0": 0, "PlayerScore1": 0, "PlayerScore10": 0, "PlayerScore11": 0, "PlayerScore2": 0, "PlayerScore3": 0, "PlayerScore4": 0, "PlayerScore5": 0, "PlayerScore6": 0, "PlayerScore7": 0, "PlayerScore8": 0, "PlayerScore9": 0, "allInPings": 9, "assistMePings": 13, "assists": 10, "baronKills": 1, "basicPings": 0, "bountyLevel": 6, "challenges": {"12AssistStreakCount": 0, "HealFromMapSources": 399.0978546142578, "InfernalScalePickup": 0, "SWARM_DefeatAatrox": 0, "SWARM_DefeatBriar": 0, "SWARM_DefeatMiniBosses": 0, "SWARM_EvolveWeapon": 0, "SWARM_Have3Passives": 0, "SWARM_KillEnemy": 0, "SWARM_PickupGold": 0, "SWARM_ReachLevel50": 0, "SWARM_Survive15Min": 0, "SWARM_WinWith5EvolvedWeapons": 0, "abilityUses": 315, "acesBefore15Minutes": 0, "alliedJungleMonsterKills": 0, "baronBuffGoldAdvantageOverThreshold": 1, "baronTakedowns": 1, "blastConeOppositeOpponentCount": 0, "bountyGold": 0, "buffsStolen": 6, "completeSupportQuestInTime": 0, "controlWardsPlaced": 0, "damagePerMinute": 510.64682634281274, "damageTakenOnTeamPercentage": 0.3138935506090261, "dancedWithRiftHerald": 0, "deathsByEnemyChamps": 5, "dodgeSkillShotsSmallWindow": 18, "doubleAces": 0, "dragonTakedowns": 4, "earliestBaron": 1562.687085109, "earliestDragonTakedown": 407.702013312, "earlyLaningPhaseGoldExpAdvantage": 1, "effectiveHealAndShielding": 317.5196838378906, "elderDragonKillsWithOpposingSoul": 0, "elderDragonMultikills": 0, "enemyChampionImmobilizations": 49, "enemyJungleMonsterKills": 0, "epicMonsterKillsNearEnemyJungler": 1, "epicMonsterKillsWithin30SecondsOfSpawn": 1, "epicMonsterSteals": 0, "epicMonsterStolenWithoutSmite": 0, "firstTurretKilled": 1, "firstTurretKilledTime": 894.243710104, "fistBumpParticipation": 1, "flawlessAces": 0, "fullTeamTakedown": 1, "gameLength": 1646.3477353120002, "goldPerMinute": 366.1613837185542, "hadOpenNexus": 0, "immobilizeAndKillWithAlly": 9, "initialBuffCount": 2, "initialCrabCount": 2, "jungleCsBefore10Minutes": 44.00000002980232, "junglerKillsEarlyJungle": 1, "junglerTakedownsNearDamagedEpicMonster": 1, "kTurretsDestroyedBeforePlatesFall": 0, "kda": 3.2, "killAfterHiddenWithAlly": 3, "killParticipation": 0.45714285714285713, "killedChampTookFullTeamDamageSurvived": 0, "killingSprees": 1, "killsNearEnemyTurret": 1, "killsOnLanersEarlyJungleAsJungler": 0, "killsOnRecentlyHealedByAramPack": 0, "killsUnderOwnTurret": 1, "killsWithHelpFromEpicMonster": 0, "knockEnemyIntoTeamAndKill": 0, "landSkillShotsEarlyGame": 7, "laneMinionsFirst10Minutes": 1, "laningPhaseGoldExpAdvantage": 0, "legendaryCount": 0, "legendaryItemUsed": [6653, 2504], "lostAnInhibitor": 0, "maxCsAdvantageOnLaneOpponent": 17, "maxKillDeficit": 2, "maxLevelLeadLaneOpponent": 2, "mejaisFullStackInTime": 0, "moreEnemyJungleThanOpponent": 0, "multiKillOneSpell": 0, "multiTurretRiftHeraldCount": 0, "multikills": 0, "multikillsAfterAggressiveFlash": 0, "outerTurretExecutesBefore10Minutes": 0, "outnumberedKills": 0, "outnumberedNexusKill": 0, "perfectDragonSoulsTaken": 1, "perfectGame": 0, "pickKillWithAlly": 14, "playedChampSelectPosition": 1, "poroExplosions": 0, "quickCleanse": 0, "quickFirstTurret": 0, "quickSoloKills": 0, "riftHeraldTakedowns": 1, "saveAllyFromDeath": 0, "scuttleCrabKills": 4, "skillshotsDodged": 122, "skillshotsHit": 83, "snowballsHit": 0, "soloBaronKills": 0, "soloKills": 0, "stealthWardsPlaced": 5, "survivedSingleDigitHpCount": 0, "survivedThreeImmobilizesInFight": 7, "takedownOnFirstTurret": 0, "takedowns": 16, "takedownsAfterGainingLevelAdvantage": 0, "takedownsBeforeJungleMinionSpawn": 0, "takedownsFirstXMinutes": 9, "takedownsInAlcove": 0, "takedownsInEnemyFountain": 0, "teamBaronKills": 1, "teamDamagePercentage": 0.16671950151235243, "teamElderDragonKills": 0, "teamRiftHeraldKills": 1, "tookLargeDamageSurvived": 0, "turretPlatesTaken": 1, "turretTakedowns": 3, "turretsTakenWithRiftHerald": 5, "twentyMinionsIn3SecondsCount": 0, "twoWardsOneSweeperCount": 0, "unseenRecalls": 0, "visionScoreAdvantageLaneOpponent": 0.10735499858856201, "visionScorePerMinute": 0.45617497927960043, "voidMonsterKill": 4, "wardTakedowns": 0, "wardTakedownsBefore20M": 0, "wardsGuarded": 1}, "champExperience": 12136, "champLevel": 14, "championId": 20, "championName": "Nunu", "championTransform": 0, "commandPings": 21, "consumablesPurchased": 0, "damageDealtToBuildings": 3703, "damageDealtToObjectives": 60651, "damageDealtToTurrets": 3703, "damageSelfMitigated": 30582, "dangerPings": 0, "deaths": 5, "detectorWardsPlaced": 0, "doubleKills": 0, "dragonKills": 2, "eligibleForProgression": true, "enemyMissingPings": 8, "enemyVisionPings": 4, "firstBloodAssist": false, "firstBloodKill": false, "firstTowerAssist": false, "firstTowerKill": false, "gameEndedInEarlySurrender": false, "gameEndedInSurrender": false, "getBackPings": 20, "goldEarned": 10047, "goldSpent": 7950, "holdPings": 0, "individualPosition": "JUNGLE", "inhibitorKills": 0, "inhibitorTakedowns": 0, "inhibitorsLost": 0, "item0": 2504, "item1": 3111, "item2": 6653, "item3": 1029, "item4": 0, "item5": 0, "item6": 3340, "itemsPurchased": 18, "killingSprees": 1, "kills": 6, "lane": "JUNGLE", "largestCriticalStrike": 0, "largestKillingSpree": 3, "largestMultiKill": 1, "longestTimeSpentLiving": 299, "magicDamageDealt": 40265, "magicDamageDealtToChampions": 11760, "magicDamageTaken": 8920, "missions": {"playerScore0": 0, "playerScore1": 0, "playerScore2": 0, "playerScore3": 0, "playerScore4": 0, "playerScore5": 0, "playerScore6": 0, "playerScore7": 0, "playerScore8": 0, "playerScore9": 0, "playerScore10": 0, "playerScore11": 0}, "needVisionPings": 1, "neutralMinionsKilled": 98, "nexusKills": 0, "nexusLost": 0, "nexusTakedowns": 1, "objectivesStolen": 0, "objectivesStolenAssists": 0, "onMyWayPings": 11, "participantId": 2, "pentaKills": 0, "perks": {"statPerks": {"defense": 5001, "flex": 5008, "offense": 5007}, "styles": [{"description": "primaryStyle", "selections": [{"perk": 8439, "var1": 504, "var2": 466, "var3": 0}, {"perk": 8463, "var1": 868, "var2": 0, "var3": 0}, {"perk": 8429, "var1": 56, "var2": 11, "var3": 13}, {"perk": 8451, "var1": 175, "var2": 0, "var3": 0}], "style": 8400}, {"description": "subStyle", "selections": [{"perk": 8126, "var1": 635, "var2": 0, "var3": 0}, {"perk": 8105, "var1": 32, "var2": 4, "var3": 0}], "style": 8100}]}, "physicalDamageDealt": 17151, "physicalDamageDealtToChampions": 1192, "physicalDamageTaken": 24000, "placement": 0, "playerAugment1": 0, "playerAugment2": 0, "playerAugment3": 0, "playerAugment4": 0, "playerAugment5": 0, "playerAugment6": 0, "playerSubteamId": 0, "profileIcon": 3374, "pushPings": 0, "puuid": "pIuKqcrPeaY9D6Vtnqsp2sdIS59C6YiYaqwXvbCHMBmCXc1vePWcrxSUYhals7YJ0VohdYjES68--A", "quadraKills": 0, "retreatPings": 3, "riotIdGameName": "Taylorrr", "riotIdTagline": "711", "role": "NONE", "sightWardsBoughtInGame": 0, "spell1Casts": 76, "spell2Casts": 65, "spell3Casts": 167, "spell4Casts": 7, "subteamPlacement": 0, "summoner1Casts": 17, "summoner1Id": 11, "summoner2Casts": 4, "summoner2Id": 4, "summonerId": "iKfVDWJwy5_oO3uYrHDn9DEtz6Q6qGaWibOQI7jbI-qLDAfvHuUrmtTP_Q", "summonerLevel": 89, "summonerName": "BHHH711", "teamEarlySurrendered": false, "teamId": 100, "teamPosition": "JUNGLE", "timeCCingOthers": 38, "timePlayed": 1646, "totalAllyJungleMinionsKilled": 0, "totalDamageDealt": 163729, "totalDamageDealtToChampions": 14011, "totalDamageShieldedOnTeammates": 0, "totalDamageTaken": 34038, "totalEnemyJungleMinionsKilled": 0, "totalHeal": 21825, "totalHealsOnTeammates": 317, "totalMinionsKilled": 20, "totalTimeCCDealt": 307, "totalTimeSpentDead": 81, "totalUnitsHealed": 5, "tripleKills": 0, "trueDamageDealt": 106312, "trueDamageDealtToChampions": 1058, "trueDamageTaken": 1116, "turretKills": 0, "turretTakedowns": 3, "turretsLost": 4, "unrealKills": 0, "visionClearedPings": 0, "visionScore": 12, "visionWardsBoughtInGame": 0, "wardsKilled": 0, "wardsPlaced": 5, "win": true}, {"PlayerScore0": 0, "PlayerScore1": 0, "PlayerScore10": 0, "PlayerScore11": 0, "PlayerScore2": 0, "PlayerScore3": 0, "PlayerScore4": 0, "PlayerScore5": 0, "PlayerScore6": 0, "PlayerScore7": 0, "PlayerScore8": 0, "PlayerScore9": 0, "allInPings": 0, "assistMePings": 0, "assists": 9, "baronKills": 0, "basicPings": 0, "bountyLevel": 8, "challenges": {"12AssistStreakCount": 0, "HealFromMapSources": 772, "InfernalScalePickup": 0, "SWARM_DefeatAatrox": 0, "SWARM_DefeatBriar": 0, "SWARM_DefeatMiniBosses": 0, "SWARM_EvolveWeapon": 0, "SWARM_Have3Passives": 0, "SWARM_KillEnemy": 0, "SWARM_PickupGold": 0, "SWARM_ReachLevel50": 0, "SWARM_Survive15Min": 0, "SWARM_WinWith5EvolvedWeapons": 0, "abilityUses": 226, "acesBefore15Minutes": 0, "alliedJungleMonsterKills": 0, "baronBuffGoldAdvantageOverThreshold": 1, "baronTakedowns": 1, "blastConeOppositeOpponentCount": 0, "bountyGold": 108.52861022949219, "buffsStolen": 0, "completeSupportQuestInTime": 0, "controlWardsPlaced": 0, "damagePerMinute": 879.622607325759, "damageTakenOnTeamPercentage": 0.10651527553787371, "dancedWithRiftHerald": 0, "deathsByEnemyChamps": 1, "dodgeSkillShotsSmallWindow": 10, "doubleAces": 0, "dragonTakedowns": 4, "earliestBaron": 1562.687085109, "earliestDragonTakedown": 407.702013312, "earlyLaningPhaseGoldExpAdvantage": 0, "effectiveHealAndShielding": 0, "elderDragonKillsWithOpposingSoul": 0, "elderDragonMultikills": 0, "enemyChampionImmobilizations": 42, "enemyJungleMonsterKills": 0, "epicMonsterKillsNearEnemyJungler": 1, "epicMonsterKillsWithin30SecondsOfSpawn": 0, "epicMonsterSteals": 0, "epicMonsterStolenWithoutSmite": 0, "fastestLegendary": 1606.21178826, "firstTurretKilled": 1, "firstTurretKilledTime": 894.243710104, "fistBumpParticipation": 1, "flawlessAces": 0, "fullTeamTakedown": 1, "gameLength": 1646.3477353120002, "getTakedownsInAllLanesEarlyJungleAsLaner": 0, "goldPerMinute": 391.4297084633666, "hadOpenNexus": 0, "highestChampionDamage": 1, "immobilizeAndKillWithAlly": 5, "initialBuffCount": 0, "initialCrabCount": 0, "jungleCsBefore10Minutes": 0, "junglerTakedownsNearDamagedEpicMonster": 1, "kTurretsDestroyedBeforePlatesFall": 0, "kda": 17, "killAfterHiddenWithAlly": 1, "killParticipation": 0.4857142857142857, "killedChampTookFullTeamDamageSurvived": 0, "killingSprees": 1, "killsNearEnemyTurret": 1, "killsOnOtherLanesEarlyJungleAsLaner": 0, "killsOnRecentlyHealedByAramPack": 0, "killsUnderOwnTurret": 2, "killsWithHelpFromEpicMonster": 0, "knockEnemyIntoTeamAndKill": 0, "landSkillShotsEarlyGame": 12, "laneMinionsFirst10Minutes": 31, "laningPhaseGoldExpAdvantage": 0, "legendaryCount": 1, "legendaryItemUsed": [6655], "lostAnInhibitor": 0, "maxCsAdvantageOnLaneOpponent": 3, "maxKillDeficit": 2, "maxLevelLeadLaneOpponent": 3, "mejaisFullStackInTime": 0, "moreEnemyJungleThanOpponent": 0, "multiKillOneSpell": 0, "multiTurretRiftHeraldCount": 0, "multikills": 0, "multikillsAfterAggressiveFlash": 0, "outerTurretExecutesBefore10Minutes": 0, "outnumberedKills": 2, "outnumberedNexusKill": 0, "perfectDragonSoulsTaken": 1, "perfectGame": 0, "pickKillWithAlly": 12, "playedChampSelectPosition": 1, "poroExplosions": 0, "quickCleanse": 0, "quickFirstTurret": 0, "quickSoloKills": 0, "riftHeraldTakedowns": 0, "saveAllyFromDeath": 0, "scuttleCrabKills": 0, "skillshotsDodged": 73, "skillshotsHit": 93, "snowballsHit": 0, "soloBaronKills": 0, "soloKills": 3, "stealthWardsPlaced": 13, "survivedSingleDigitHpCount": 0, "survivedThreeImmobilizesInFight": 10, "takedownOnFirstTurret": 0, "takedowns": 17, "takedownsAfterGainingLevelAdvantage": 0, "takedownsBeforeJungleMinionSpawn": 0, "takedownsFirstXMinutes": 10, "takedownsInAlcove": 0, "takedownsInEnemyFountain": 0, "teamBaronKills": 1, "teamDamagePercentage": 0.2871852619992501, "teamElderDragonKills": 0, "teamRiftHeraldKills": 1, "tookLargeDamageSurvived": 0, "turretPlatesTaken": 2, "turretTakedowns": 4, "turretsTakenWithRiftHerald": 5, "twentyMinionsIn3SecondsCount": 0, "twoWardsOneSweeperCount": 0, "unseenRecalls": 0, "visionScoreAdvantageLaneOpponent": 1.103968620300293, "visionScorePerMinute": 0.8491050941770883, "voidMonsterKill": 1, "wardTakedowns": 0, "wardTakedownsBefore20M": 0, "wardsGuarded": 0}, "champExperience": 14094, "champLevel": 15, "championId": 711, "championName": "Vex", "championTransform": 0, "commandPings": 3, "consumablesPurchased": 4, "damageDealtToBuildings": 4542, "damageDealtToObjectives": 10069, "damageDealtToTurrets": 4542, "damageSelfMitigated": 7660, "dangerPings": 0, "deaths": 1, "detectorWardsPlaced": 0, "doubleKills": 0, "dragonKills": 1, "eligibleForProgression": true, "enemyMissingPings": 3, "enemyVisionPings": 0, "firstBloodAssist": false, "firstBloodKill": false, "firstTowerAssist": false, "firstTowerKill": false, "gameEndedInEarlySurrender": false, "gameEndedInSurrender": false, "getBackPings": 0, "goldEarned": 10740, "goldSpent": 6850, "holdPings": 0, "individualPosition": "MIDDLE", "inhibitorKills": 0, "inhibitorTakedowns": 1, "inhibitorsLost": 0, "item0": 3020, "item1": 1056, "item2": 6655, "item3": 3145, "item4": 1058, "item5": 0, "item6": 3340, "itemsPurchased": 17, "killingSprees": 1, "kills": 8, "lane": "MIDDLE", "largestCriticalStrike": 0, "largestKillingSpree": 8, "largestMultiKill": 1, "longestTimeSpentLiving": 420, "magicDamageDealt": 104415, "magicDamageDealtToChampions": 21021, "magicDamageTaken": 5349, "missions": {"playerScore0": 0, "playerScore1": 0, "playerScore2": 0, "playerScore3": 0, "playerScore4": 0, "playerScore5": 0, "playerScore6": 0, "playerScore7": 0, "playerScore8": 0, "playerScore9": 0, "playerScore10": 0, "playerScore11": 0}, "needVisionPings": 0, "neutralMinionsKilled": 4, "nexusKills": 0, "nexusLost": 0, "nexusTakedowns": 1, "objectivesStolen": 0, "objectivesStolenAssists": 0, "onMyWayPings": 6, "participantId": 3, "pentaKills": 0, "perks": {"statPerks": {"defense": 5001, "flex": 5008, "offense": 5005}, "styles": [{"description": "primaryStyle", "selections": [{"perk": 8112, "var1": 1438, "var2": 0, "var3": 0}, {"perk": 8139, "var1": 948, "var2": 0, "var3": 0}, {"perk": 8140, "var1": 17, "var2": 0, "var3": 0}, {"perk": 8106, "var1": 5, "var2": 31, "var3": 0}], "style": 8100}, {"description": "subStyle", "selections": [{"perk": 8226, "var1": 250, "var2": 1114, "var3": 0}, {"perk": 8210, "var1": 16, "var2": 0, "var3": 0}], "style": 8200}]}, "physicalDamageDealt": 18562, "physicalDamageDealtToChampions": 2156, "physicalDamageTaken": 5671, "placement": 0, "playerAugment1": 0, "playerAugment2": 0, "playerAugment3": 0, "playerAugment4": 0, "playerAugment5": 0, "playerAugment6": 0, "playerSubteamId": 0, "profileIcon": 3383, "pushPings": 0, "puuid": "Q7x_1N1S0SGqvelbZVYpV2Py6b7Oa16BoMnCsk_ozv7SuHMCxgYmWvyWRv2C_Pit1X6sCf38aS_yTw", "quadraKills": 0, "retreatPings": 1, "riotIdGameName": "SLEEPYHALLO", "riotIdTagline": "NA1", "role": "SOLO", "sightWardsBoughtInGame": 0, "spell1Casts": 112, "spell2Casts": 26, "spell3Casts": 68, "spell4Casts": 20, "subteamPlacement": 0, "summoner1Casts": 5, "summoner1Id": 14, "summoner2Casts": 3, "summoner2Id": 4, "summonerId": "VJQOdhaRD2wbdplNc0cG6ffPykdr-KMaI79FXUH-PSs-ltmJ", "summonerLevel": 517, "summonerName": "SLEEPYHALLO", "teamEarlySurrendered": false, "teamId": 100, "teamPosition": "MIDDLE", "timeCCingOthers": 40, "timePlayed": 1646, "totalAllyJungleMinionsKilled": 0, "totalDamageDealt": 124475, "totalDamageDealtToChampions": 24136, "totalDamageShieldedOnTeammates": 0, "totalDamageTaken": 11550, "totalEnemyJungleMinionsKilled": 0, "totalHeal": 3934, "totalHealsOnTeammates": 0, "totalMinionsKilled": 131, "totalTimeCCDealt": 487, "totalTimeSpentDead": 16, "totalUnitsHealed": 1, "tripleKills": 0, "trueDamageDealt": 1498, "trueDamageDealtToChampions": 958, "trueDamageTaken": 529, "turretKills": 2, "turretTakedowns": 4, "turretsLost": 4, "unrealKills": 0, "visionClearedPings": 0, "visionScore": 23, "visionWardsBoughtInGame": 0, "wardsKilled": 0, "wardsPlaced": 14, "win": true}, {"PlayerScore0": 0, "PlayerScore1": 0, "PlayerScore10": 0, "PlayerScore11": 0, "PlayerScore2": 0, "PlayerScore3": 0, "PlayerScore4": 0, "PlayerScore5": 0, "PlayerScore6": 0, "PlayerScore7": 0, "PlayerScore8": 0, "PlayerScore9": 0, "allInPings": 0, "assistMePings": 1, "assists": 6, "baronKills": 0, "basicPings": 0, "bountyLevel": 12, "challenges": {"12AssistStreakCount": 0, "HealFromMapSources": 502, "InfernalScalePickup": 0, "SWARM_DefeatAatrox": 0, "SWARM_DefeatBriar": 0, "SWARM_DefeatMiniBosses": 0, "SWARM_EvolveWeapon": 0, "SWARM_Have3Passives": 0, "SWARM_KillEnemy": 0, "SWARM_PickupGold": 0, "SWARM_ReachLevel50": 0, "SWARM_Survive15Min": 0, "SWARM_WinWith5EvolvedWeapons": 0, "abilityUses": 109, "acesBefore15Minutes": 0, "alliedJungleMonsterKills": 0, "baronBuffGoldAdvantageOverThreshold": 1, "baronTakedowns": 1, "blastConeOppositeOpponentCount": 0, "bountyGold": 0, "buffsStolen": 0, "completeSupportQuestInTime": 0, "controlWardsPlaced": 0, "damagePerMinute": 828.1198990164289, "damageTakenOnTeamPercentage": 0.1677301944615865, "dancedWithRiftHerald": 0, "deathsByEnemyChamps": 5, "dodgeSkillShotsSmallWindow": 5, "doubleAces": 0, "dragonTakedowns": 4, "earliestBaron": 1562.687085109, "earliestDragonTakedown": 407.702013312, "earlyLaningPhaseGoldExpAdvantage": 0, "effectiveHealAndShielding": 0, "elderDragonKillsWithOpposingSoul": 0, "elderDragonMultikills": 0, "enemyChampionImmobilizations": 14, "enemyJungleMonsterKills": 0, "epicMonsterKillsNearEnemyJungler": 0, "epicMonsterKillsWithin30SecondsOfSpawn": 0, "epicMonsterSteals": 0, "epicMonsterStolenWithoutSmite": 0, "firstTurretKilled": 1, "firstTurretKilledTime": 894.243710104, "fistBumpParticipation": 0, "flawlessAces": 0, "fullTeamTakedown": 1, "gameLength": 1646.3477353120002, "getTakedownsInAllLanesEarlyJungleAsLaner": 0, "goldPerMinute": 487.37813373715244, "hadOpenNexus": 0, "immobilizeAndKillWithAlly": 2, "initialBuffCount": 0, "initialCrabCount": 0, "jungleCsBefore10Minutes": 0, "junglerTakedownsNearDamagedEpicMonster": 1, "kTurretsDestroyedBeforePlatesFall": 0, "kda": 3.6, "killAfterHiddenWithAlly": 1, "killParticipation": 0.5142857142857142, "killedChampTookFullTeamDamageSurvived": 0, "killingSprees": 2, "killsNearEnemyTurret": 2, "killsOnOtherLanesEarlyJungleAsLaner": 0, "killsOnRecentlyHealedByAramPack": 0, "killsUnderOwnTurret": 1, "killsWithHelpFromEpicMonster": 0, "knockEnemyIntoTeamAndKill": 3, "landSkillShotsEarlyGame": 0, "laneMinionsFirst10Minutes": 35, "laningPhaseGoldExpAdvantage": 0, "legendaryCount": 0, "legendaryItemUsed": [6676, 3094, 3036], "lostAnInhibitor": 0, "maxCsAdvantageOnLaneOpponent": 13.000000059604645, "maxKillDeficit": 2, "maxLevelLeadLaneOpponent": 3, "mejaisFullStackInTime": 0, "moreEnemyJungleThanOpponent": 0, "multiKillOneSpell": 0, "multiTurretRiftHeraldCount": 0, "multikills": 2, "multikillsAfterAggressiveFlash": 0, "outerTurretExecutesBefore10Minutes": 0, "outnumberedKills": 2, "outnumberedNexusKill": 0, "perfectDragonSoulsTaken": 1, "perfectGame": 0, "pickKillWithAlly": 12, "playedChampSelectPosition": 1, "poroExplosions": 0, "quickCleanse": 0, "quickFirstTurret": 0, "quickSoloKills": 0, "riftHeraldTakedowns": 0, "saveAllyFromDeath": 0, "scuttleCrabKills": 0, "skillshotsDodged": 68, "skillshotsHit": 0, "snowballsHit": 0, "soloBaronKills": 0, "soloKills": 3, "soloTurretsLategame": 1, "stealthWardsPlaced": 8, "survivedSingleDigitHpCount": 0, "survivedThreeImmobilizesInFight": 0, "takedownOnFirstTurret": 0, "takedowns": 18, "takedownsAfterGainingLevelAdvantage": 0, "takedownsBeforeJungleMinionSpawn": 0, "takedownsFirstXMinutes": 11, "takedownsInAlcove": 0, "takedownsInEnemyFountain": 1, "teamBaronKills": 1, "teamDamagePercentage": 0.27037030220137365, "teamElderDragonKills": 0, "teamRiftHeraldKills": 1, "tookLargeDamageSurvived": 0, "turretPlatesTaken": 1, "turretTakedowns": 6, "turretsTakenWithRiftHerald": 5, "twentyMinionsIn3SecondsCount": 0, "twoWardsOneSweeperCount": 0, "unseenRecalls": 0, "visionScoreAdvantageLaneOpponent": -0.07927906513214111, "visionScorePerMinute": 0.52278815171876, "voidMonsterKill": 1, "wardTakedowns": 1, "wardTakedownsBefore20M": 1, "wardsGuarded": 1}, "champExperience": 13287, "champLevel": 15, "championId": 18, "championName": "Tristana", "championTransform": 0, "commandPings": 7, "consumablesPurchased": 11, "damageDealtToBuildings": 12175, "damageDealtToObjectives": 24766, "damageDealtToTurrets": 12175, "damageSelfMitigated": 9538, "dangerPings": 0, "deaths": 5, "detectorWardsPlaced": 0, "doubleKills": 2, "dragonKills": 0, "eligibleForProgression": true, "enemyMissingPings": 0, "enemyVisionPings": 0, "firstBloodAssist": false, "firstBloodKill": false, "firstTowerAssist": true, "firstTowerKill": false, "gameEndedInEarlySurrender": false, "gameEndedInSurrender": false, "getBackPings": 0, "goldEarned": 13373, "goldSpent": 12900, "holdPings": 0, "individualPosition": "BOTTOM", "inhibitorKills": 1, "inhibitorTakedowns": 2, "inhibitorsLost": 0, "item0": 3036, "item1": 6676, "item2": 1038, "item3": 3094, "item4": 0, "item5": 3172, "item6": 3340, "itemsPurchased": 27, "killingSprees": 3, "kills": 12, "lane": "BOTTOM", "largestCriticalStrike": 444, "largestKillingSpree": 6, "largestMultiKill": 2, "longestTimeSpentLiving": 506, "magicDamageDealt": 19359, "magicDamageDealtToChampions": 3803, "magicDamageTaken": 3873, "missions": {"playerScore0": 0, "playerScore1": 0, "playerScore2": 0, "playerScore3": 0, "playerScore4": 0, "playerScore5": 0, "playerScore6": 0, "playerScore7": 0, "playerScore8": 0, "playerScore9": 0, "playerScore10": 0, "playerScore11": 0}, "needVisionPings": 0, "neutralMinionsKilled": 6, "nexusKills": 0, "nexusLost": 0, "nexusTakedowns": 0, "objectivesStolen": 0, "objectivesStolenAssists": 0, "onMyWayPings": 2, "participantId": 4, "pentaKills": 0, "perks": {"statPerks": {"defense": 5001, "flex": 5008, "offense": 5005}, "styles": [{"description": "primaryStyle", "selections": [{"perk": 8005, "var1": 1170, "var2": 1170, "var3": 0}, {"perk": 9111, "var1": 1131, "var2": 360, "var3": 0}, {"perk": 9104, "var1": 12, "var2": 0, "var3": 0}, {"perk": 8014, "var1": 492, "var2": 0, "var3": 0}], "style": 8000}, {"description": "subStyle", "selections": [{"perk": 8139, "var1": 712, "var2": 0, "var3": 0}, {"perk": 8135, "var1": 320, "var2": 4, "var3": 0}], "style": 8100}]}, "physicalDamageDealt": 116983, "physicalDamageDealtToChampions": 17729, "physicalDamageTaken": 13523, "placement": 0, "playerAugment1": 0, "playerAugment2": 0, "playerAugment3": 0, "playerAugment4": 0, "playerAugment5": 0, "playerAugment6": 0, "playerSubteamId": 0, "profileIcon": 6107, "pushPings": 0, "puuid": "K2-lKPBNbJoGtnTOi47zVmAbv8XnHxUOwYUIPLeFMIOVRA1AVFnUXIHr4DoVoPUobsYMNYn3CN5i7g", "quadraKills": 0, "retreatPings": 0, "riotIdGameName": "BlacKamenRiders", "riotIdTagline": "NA1", "role": "CARRY", "sightWardsBoughtInGame": 0, "spell1Casts": 29, "spell2Casts": 34, "spell3Casts": 38, "spell4Casts": 8, "subteamPlacement": 0, "summoner1Casts": 7, "summoner1Id": 14, "summoner2Casts": 4, "summoner2Id": 4, "summonerId": "KUfMCMTYVvIOYlsFUVwhkThWmMwZnlOK_3vnHUIlMyLc4HlJop9A4cl0lg", "summonerLevel": 263, "summonerName": "BlacKamenRiders", "teamEarlySurrendered": false, "teamId": 100, "teamPosition": "BOTTOM", "timeCCingOthers": 8, "timePlayed": 1646, "totalAllyJungleMinionsKilled": 0, "totalDamageDealt": 149639, "totalDamageDealtToChampions": 22722, "totalDamageShieldedOnTeammates": 0, "totalDamageTaken": 18188, "totalEnemyJungleMinionsKilled": 0, "totalHeal": 5803, "totalHealsOnTeammates": 0, "totalMinionsKilled": 152, "totalTimeCCDealt": 55, "totalTimeSpentDead": 105, "totalUnitsHealed": 1, "tripleKills": 0, "trueDamageDealt": 13296, "trueDamageDealtToChampions": 1190, "trueDamageTaken": 791, "turretKills": 4, "turretTakedowns": 6, "turretsLost": 4, "unrealKills": 0, "visionClearedPings": 0, "visionScore": 14, "visionWardsBoughtInGame": 0, "wardsKilled": 1, "wardsPlaced": 8, "win": true}, {"PlayerScore0": 0, "PlayerScore1": 0, "PlayerScore10": 0, "PlayerScore11": 0, "PlayerScore2": 0, "PlayerScore3": 0, "PlayerScore4": 0, "PlayerScore5": 0, "PlayerScore6": 0, "PlayerScore7": 0, "PlayerScore8": 0, "PlayerScore9": 0, "allInPings": 1, "assistMePings": 4, "assists": 15, "baronKills": 0, "basicPings": 0, "bountyLevel": 4, "challenges": {"12AssistStreakCount": 0, "HealFromMapSources": 808.1724624633789, "InfernalScalePickup": 0, "SWARM_DefeatAatrox": 0, "SWARM_DefeatBriar": 0, "SWARM_DefeatMiniBosses": 0, "SWARM_EvolveWeapon": 0, "SWARM_Have3Passives": 0, "SWARM_KillEnemy": 0, "SWARM_PickupGold": 0, "SWARM_ReachLevel50": 0, "SWARM_Survive15Min": 0, "SWARM_WinWith5EvolvedWeapons": 0, "abilityUses": 187, "acesBefore15Minutes": 0, "alliedJungleMonsterKills": 0, "baronBuffGoldAdvantageOverThreshold": 1, "baronTakedowns": 1, "blastConeOppositeOpponentCount": 0, "bountyGold": 0, "buffsStolen": 0, "completeSupportQuestInTime": 0, "controlWardsPlaced": 1, "damagePerMinute": 263.28053259757206, "damageTakenOnTeamPercentage": 0.17063365406940476, "dancedWithRiftHerald": 0, "deathsByEnemyChamps": 1, "dodgeSkillShotsSmallWindow": 2, "doubleAces": 0, "dragonTakedowns": 3, "earliestBaron": 1562.687085109, "earliestDragonTakedown": 407.702013312, "earlyLaningPhaseGoldExpAdvantage": 0, "effectiveHealAndShielding": 4640.3603515625, "elderDragonKillsWithOpposingSoul": 0, "elderDragonMultikills": 0, "enemyChampionImmobilizations": 10, "enemyJungleMonsterKills": 0, "epicMonsterKillsNearEnemyJungler": 0, "epicMonsterKillsWithin30SecondsOfSpawn": 0, "epicMonsterSteals": 0, "epicMonsterStolenWithoutSmite": 0, "firstTurretKilled": 1, "firstTurretKilledTime": 894.243710104, "fistBumpParticipation": 0, "flawlessAces": 0, "fullTeamTakedown": 1, "gameLength": 1646.3477353120002, "getTakedownsInAllLanesEarlyJungleAsLaner": 0, "goldPerMinute": 336.2670522914071, "hadOpenNexus": 0, "highestWardKills": 1, "immobilizeAndKillWithAlly": 5, "initialBuffCount": 0, "initialCrabCount": 0, "jungleCsBefore10Minutes": 0, "junglerTakedownsNearDamagedEpicMonster": 0, "kTurretsDestroyedBeforePlatesFall": 0, "kda": 19, "killAfterHiddenWithAlly": 1, "killParticipation": 0.5428571428571428, "killedChampTookFullTeamDamageSurvived": 0, "killingSprees": 1, "killsNearEnemyTurret": 0, "killsOnOtherLanesEarlyJungleAsLaner": 0, "killsOnRecentlyHealedByAramPack": 0, "killsUnderOwnTurret": 1, "killsWithHelpFromEpicMonster": 0, "knockEnemyIntoTeamAndKill": 0, "landSkillShotsEarlyGame": 7, "laneMinionsFirst10Minutes": 18, "laningPhaseGoldExpAdvantage": 0, "legendaryCount": 0, "legendaryItemUsed": [6617, 3870, 3118], "lostAnInhibitor": 0, "maxCsAdvantageOnLaneOpponent": 17, "maxKillDeficit": 2, "maxLevelLeadLaneOpponent": 2, "mejaisFullStackInTime": 0, "moreEnemyJungleThanOpponent": 0, "multiKillOneSpell": 0, "multiTurretRiftHeraldCount": 0, "multikills": 0, "multikillsAfterAggressiveFlash": 0, "outerTurretExecutesBefore10Minutes": 0, "outnumberedKills": 1, "outnumberedNexusKill": 0, "perfectDragonSoulsTaken": 1, "perfectGame": 0, "pickKillWithAlly": 15, "playedChampSelectPosition": 1, "poroExplosions": 0, "quickCleanse": 0, "quickFirstTurret": 0, "quickSoloKills": 0, "riftHeraldTakedowns": 0, "saveAllyFromDeath": 2, "scuttleCrabKills": 0, "skillshotsDodged": 50, "skillshotsHit": 19, "snowballsHit": 0, "soloBaronKills": 0, "soloKills": 1, "stealthWardsPlaced": 16, "survivedSingleDigitHpCount": 0, "survivedThreeImmobilizesInFight": 2, "takedownOnFirstTurret": 1, "takedowns": 19, "takedownsAfterGainingLevelAdvantage": 0, "takedownsBeforeJungleMinionSpawn": 0, "takedownsFirstXMinutes": 9, "takedownsInAlcove": 0, "takedownsInEnemyFountain": 0, "teamBaronKills": 1, "teamDamagePercentage": 0.08595764604460009, "teamElderDragonKills": 0, "teamRiftHeraldKills": 1, "tookLargeDamageSurvived": 0, "turretPlatesTaken": 1, "turretTakedowns": 3, "turretsTakenWithRiftHerald": 5, "twentyMinionsIn3SecondsCount": 0, "twoWardsOneSweeperCount": 0, "unseenRecalls": 0, "visionScoreAdvantageLaneOpponent": 0.8962544202804565, "visionScorePerMinute": 1.4783159387145424, "voidMonsterKill": 1, "wardTakedowns": 3, "wardTakedownsBefore20M": 3, "wardsGuarded": 1}, "champExperience": 10829, "champLevel": 13, "championId": 43, "championName": "Karma", "championTransform": 0, "commandPings": 2, "consumablesPurchased": 3, "damageDealtToBuildings": 988, "damageDealtToObjectives": 6179, "damageDealtToTurrets": 988, "damageSelfMitigated": 12501, "dangerPings": 0, "deaths": 1, "detectorWardsPlaced": 1, "doubleKills": 0, "dragonKills": 0, "eligibleForProgression": true, "enemyMissingPings": 2, "enemyVisionPings": 0, "firstBloodAssist": false, "firstBloodKill": false, "firstTowerAssist": false, "firstTowerKill": false, "gameEndedInEarlySurrender": false, "gameEndedInSurrender": false, "getBackPings": 6, "goldEarned": 9226, "goldSpent": 8425, "holdPings": 0, "individualPosition": "UTILITY", "inhibitorKills": 0, "inhibitorTakedowns": 0, "inhibitorsLost": 0, "item0": 3870, "item1": 3171, "item2": 6617, "item3": 3118, "item4": 4642, "item5": 1052, "item6": 3364, "itemsPurchased": 18, "killingSprees": 1, "kills": 4, "lane": "BOTTOM", "largestCriticalStrike": 0, "largestKillingSpree": 4, "largestMultiKill": 1, "longestTimeSpentLiving": 1195, "magicDamageDealt": 24316, "magicDamageDealtToChampions": 6097, "magicDamageTaken": 9018, "missions": {"playerScore0": 0, "playerScore1": 0, "playerScore2": 0, "playerScore3": 0, "playerScore4": 0, "playerScore5": 0, "playerScore6": 0, "playerScore7": 0, "playerScore8": 0, "playerScore9": 0, "playerScore10": 0, "playerScore11": 0}, "needVisionPings": 0, "neutralMinionsKilled": 4, "nexusKills": 1, "nexusLost": 0, "nexusTakedowns": 1, "objectivesStolen": 0, "objectivesStolenAssists": 0, "onMyWayPings": 14, "participantId": 5, "pentaKills": 0, "perks": {"statPerks": {"defense": 5011, "flex": 5008, "offense": 5008}, "styles": [{"description": "primaryStyle", "selections": [{"perk": 8229, "var1": 728, "var2": 0, "var3": 0}, {"perk": 8224, "var1": 9, "var2": 1480, "var3": 0}, {"perk": 8210, "var1": 3, "var2": 0, "var3": 0}, {"perk": 8237, "var1": 289, "var2": 0, "var3": 0}], "style": 8200}, {"description": "subStyle", "selections": [{"perk": 8345, "var1": 3, "var2": 0, "var3": 146}, {"perk": 8347, "var1": 0, "var2": 0, "var3": 0}], "style": 8300}]}, "physicalDamageDealt": 6009, "physicalDamageDealtToChampions": 1127, "physicalDamageTaken": 8925, "placement": 0, "playerAugment1": 0, "playerAugment2": 0, "playerAugment3": 0, "playerAugment4": 0, "playerAugment5": 0, "playerAugment6": 0, "playerSubteamId": 0, "profileIcon": 2072, "pushPings": 1, "puuid": "Fkn8VJYa2kbHJOyRVQOQNayOG4uIbnUvKWucwpEM7RYYWvsAnvCO5VcaIL5lnyW-G2CanV8XjCz8Sw", "quadraKills": 0, "retreatPings": 0, "riotIdGameName": "Milk", "riotIdTagline": "223", "role": "SUPPORT", "sightWardsBoughtInGame": 0, "spell1Casts": 59, "spell2Casts": 22, "spell3Casts": 93, "spell4Casts": 13, "subteamPlacement": 0, "summoner1Casts": 6, "summoner1Id": 7, "summoner2Casts": 4, "summoner2Id": 4, "summonerId": "X-uq6VcbRuIdit-Ddf_qrQPzCajlYzscfAYTk2RfzaTFyhUNc89QP8ynQg", "summonerLevel": 127, "summonerName": "", "teamEarlySurrendered": false, "teamId": 100, "teamPosition": "UTILITY", "timeCCingOthers": 20, "timePlayed": 1646, "totalAllyJungleMinionsKilled": 0, "totalDamageDealt": 34437, "totalDamageDealtToChampions": 7224, "totalDamageShieldedOnTeammates": 4169, "totalDamageTaken": 18503, "totalEnemyJungleMinionsKilled": 0, "totalHeal": 6809, "totalHealsOnTeammates": 471, "totalMinionsKilled": 40, "totalTimeCCDealt": 112, "totalTimeSpentDead": 36, "totalUnitsHealed": 2, "tripleKills": 0, "trueDamageDealt": 4111, "trueDamageDealtToChampions": 0, "trueDamageTaken": 559, "turretKills": 1, "turretTakedowns": 3, "turretsLost": 4, "unrealKills": 0, "visionClearedPings": 0, "visionScore": 40, "visionWardsBoughtInGame": 1, "wardsKilled": 3, "wardsPlaced": 17, "win": true}, {"PlayerScore0": 0, "PlayerScore1": 0, "PlayerScore10": 0, "PlayerScore11": 0, "PlayerScore2": 0, "PlayerScore3": 0, "PlayerScore4": 0, "PlayerScore5": 0, "PlayerScore6": 0, "PlayerScore7": 0, "PlayerScore8": 0, "PlayerScore9": 0, "allInPings": 2, "assistMePings": 4, "assists": 3, "baronKills": 0, "basicPings": 0, "bountyLevel": 0, "challenges": {"12AssistStreakCount": 0, "HealFromMapSources": 0, "InfernalScalePickup": 0, "SWARM_DefeatAatrox": 0, "SWARM_DefeatBriar": 0, "SWARM_DefeatMiniBosses": 0, "SWARM_EvolveWeapon": 0, "SWARM_Have3Passives": 0, "SWARM_KillEnemy": 0, "SWARM_PickupGold": 0, "SWARM_ReachLevel50": 0, "SWARM_Survive15Min": 0, "SWARM_WinWith5EvolvedWeapons": 0, "abilityUses": 148, "acesBefore15Minutes": 0, "alliedJungleMonsterKills": 0, "baronTakedowns": 0, "blastConeOppositeOpponentCount": 0, "bountyGold": 0, "buffsStolen": 1, "completeSupportQuestInTime": 0, "controlWardTimeCoverageInRiverOrEnemyHalf": 0.33051785691124264, "controlWardsPlaced": 1, "damagePerMinute": 458.8987951833417, "damageTakenOnTeamPercentage": 0.22212974724742957, "dancedWithRiftHerald": 0, "deathsByEnemyChamps": 2, "dodgeSkillShotsSmallWindow": 1, "doubleAces": 0, "dragonTakedowns": 0, "earlyLaningPhaseGoldExpAdvantage": 0, "effectiveHealAndShielding": 0, "elderDragonKillsWithOpposingSoul": 0, "elderDragonMultikills": 0, "enemyChampionImmobilizations": 0, "enemyJungleMonsterKills": 0, "epicMonsterKillsNearEnemyJungler": 0, "epicMonsterKillsWithin30SecondsOfSpawn": 0, "epicMonsterSteals": 0, "epicMonsterStolenWithoutSmite": 0, "firstTurretKilled": 0, "fistBumpParticipation": 0, "flawlessAces": 0, "fullTeamTakedown": 0, "gameLength": 1646.3477353120002, "getTakedownsInAllLanesEarlyJungleAsLaner": 0, "goldPerMinute": 322.74048489856546, "hadOpenNexus": 0, "immobilizeAndKillWithAlly": 0, "initialBuffCount": 0, "initialCrabCount": 0, "jungleCsBefore10Minutes": 0, "junglerTakedownsNearDamagedEpicMonster": 0, "kTurretsDestroyedBeforePlatesFall": 0, "kda": 1.5, "killAfterHiddenWithAlly": 0, "killParticipation": 0.25, "killedChampTookFullTeamDamageSurvived": 0, "killingSprees": 0, "killsNearEnemyTurret": 0, "killsOnOtherLanesEarlyJungleAsLaner": 0, "killsOnRecentlyHealedByAramPack": 0, "killsUnderOwnTurret": 0, "killsWithHelpFromEpicMonster": 0, "knockEnemyIntoTeamAndKill": 0, "landSkillShotsEarlyGame": 0, "laneMinionsFirst10Minutes": 55, "laningPhaseGoldExpAdvantage": 0, "legendaryCount": 0, "legendaryItemUsed": [6631], "lostAnInhibitor": 0, "maxCsAdvantageOnLaneOpponent": 27, "maxKillDeficit": 0, "maxLevelLeadLaneOpponent": 1, "mejaisFullStackInTime": 0, "moreEnemyJungleThanOpponent": 0, "multiKillOneSpell": 0, "multiTurretRiftHeraldCount": 0, "multikills": 0, "multikillsAfterAggressiveFlash": 0, "outerTurretExecutesBefore10Minutes": 0, "outnumberedKills": 0, "outnumberedNexusKill": 0, "perfectDragonSoulsTaken": 0, "perfectGame": 0, "pickKillWithAlly": 3, "playedChampSelectPosition": 1, "poroExplosions": 0, "quickCleanse": 0, "quickFirstTurret": 0, "quickSoloKills": 0, "riftHeraldTakedowns": 0, "saveAllyFromDeath": 0, "scuttleCrabKills": 1, "skillshotsDodged": 10, "skillshotsHit": 0, "snowballsHit": 0, "soloBaronKills": 0, "soloKills": 0, "soloTurretsLategame": 1, "stealthWardsPlaced": 4, "survivedSingleDigitHpCount": 0, "survivedThreeImmobilizesInFight": 6, "takedownOnFirstTurret": 0, "takedowns": 3, "takedownsAfterGainingLevelAdvantage": 0, "takedownsBeforeJungleMinionSpawn": 0, "takedownsFirstXMinutes": 2, "takedownsInAlcove": 0, "takedownsInEnemyFountain": 0, "teamBaronKills": 0, "teamDamagePercentage": 0.19022980209941698, "teamElderDragonKills": 0, "teamRiftHeraldKills": 0, "tookLargeDamageSurvived": 0, "turretPlatesTaken": 3, "turretTakedowns": 3, "turretsTakenWithRiftHerald": 0, "twentyMinionsIn3SecondsCount": 0, "twoWardsOneSweeperCount": 0, "unseenRecalls": 0, "visionScoreAdvantageLaneOpponent": 0.010793209075927734, "visionScorePerMinute": 0.4714092631824098, "voidMonsterKill": 0, "wardTakedowns": 0, "wardTakedownsBefore20M": 0, "wardsGuarded": 1}, "champExperience": 11132, "champLevel": 13, "championId": 86, "championName": "Garen", "championTransform": 0, "commandPings": 5, "consumablesPurchased": 2, "damageDealtToBuildings": 4855, "damageDealtToObjectives": 4855, "damageDealtToTurrets": 4855, "damageSelfMitigated": 27055, "dangerPings": 0, "deaths": 2, "detectorWardsPlaced": 1, "doubleKills": 0, "dragonKills": 0, "eligibleForProgression": true, "enemyMissingPings": 4, "enemyVisionPings": 1, "firstBloodAssist": false, "firstBloodKill": false, "firstTowerAssist": false, "firstTowerKill": false, "gameEndedInEarlySurrender": false, "gameEndedInSurrender": false, "getBackPings": 0, "goldEarned": 8855, "goldSpent": 8425, "holdPings": 0, "individualPosition": "TOP", "inhibitorKills": 0, "inhibitorTakedowns": 0, "inhibitorsLost": 2, "item0": 1054, "item1": 6631, "item2": 3006, "item3": 3066, "item4": 3035, "item5": 3123, "item6": 3364, "itemsPurchased": 18, "killingSprees": 0, "kills": 0, "lane": "TOP", "largestCriticalStrike": 0, "largestKillingSpree": 0, "largestMultiKill": 0, "longestTimeSpentLiving": 1009, "magicDamageDealt": 0, "magicDamageDealtToChampions": 0, "magicDamageTaken": 9493, "missions": {"playerScore0": 0, "playerScore1": 0, "playerScore2": 0, "playerScore3": 0, "playerScore4": 0, "playerScore5": 0, "playerScore6": 0, "playerScore7": 0, "playerScore8": 0, "playerScore9": 0, "playerScore10": 0, "playerScore11": 0}, "needVisionPings": 0, "neutralMinionsKilled": 13, "nexusKills": 0, "nexusLost": 1, "nexusTakedowns": 0, "objectivesStolen": 0, "objectivesStolenAssists": 0, "onMyWayPings": 0, "participantId": 6, "pentaKills": 0, "perks": {"statPerks": {"defense": 5001, "flex": 5008, "offense": 5008}, "styles": [{"description": "primaryStyle", "selections": [{"perk": 8010, "var1": 428, "var2": 0, "var3": 0}, {"perk": 9111, "var1": 164, "var2": 60, "var3": 0}, {"perk": 9105, "var1": 0, "var2": 0, "var3": 0}, {"perk": 8299, "var1": 35, "var2": 0, "var3": 0}], "style": 8000}, {"description": "subStyle", "selections": [{"perk": 8429, "var1": 56, "var2": 11, "var3": 10}, {"perk": 8451, "var1": 198, "var2": 0, "var3": 0}], "style": 8400}]}, "physicalDamageDealt": 106714, "physicalDamageDealtToChampions": 10852, "physicalDamageTaken": 14324, "placement": 0, "playerAugment1": 0, "playerAugment2": 0, "playerAugment3": 0, "playerAugment4": 0, "playerAugment5": 0, "playerAugment6": 0, "playerSubteamId": 0, "profileIcon": 986, "pushPings": 0, "puuid": "_6ZrpSOpHysz_IStR7shXbSV_1cCQN28AlvCS2kgLznZD8O7BF_N8-6sj6oPffc_FUugjwgcydh_zA", "quadraKills": 0, "retreatPings": 0, "riotIdGameName": "Black XxX Plague", "riotIdTagline": "NA1", "role": "SOLO", "sightWardsBoughtInGame": 0, "spell1Casts": 78, "spell2Casts": 18, "spell3Casts": 50, "spell4Casts": 2, "subteamPlacement": 0, "summoner1Casts": 5, "summoner1Id": 14, "summoner2Casts": 5, "summoner2Id": 4, "summonerId": "kAk_LtTzrT98xnUWnxzar-zWD7xWE_eltmX2GlPbvlHhXzpeU9JELm_jsA", "summonerLevel": 62, "summonerName": "Black XxX Plague", "teamEarlySurrendered": false, "teamId": 200, "teamPosition": "TOP", "timeCCingOthers": 30, "timePlayed": 1646, "totalAllyJungleMinionsKilled": 0, "totalDamageDealt": 108821, "totalDamageDealtToChampions": 12591, "totalDamageShieldedOnTeammates": 0, "totalDamageTaken": 24530, "totalEnemyJungleMinionsKilled": 0, "totalHeal": 545, "totalHealsOnTeammates": 0, "totalMinionsKilled": 156, "totalTimeCCDealt": 115, "totalTimeSpentDead": 71, "totalUnitsHealed": 1, "tripleKills": 0, "trueDamageDealt": 2106, "trueDamageDealtToChampions": 1738, "trueDamageTaken": 712, "turretKills": 1, "turretTakedowns": 3, "turretsLost": 9, "unrealKills": 0, "visionClearedPings": 0, "visionScore": 12, "visionWardsBoughtInGame": 1, "wardsKilled": 0, "wardsPlaced": 5, "win": false}, {"PlayerScore0": 0, "PlayerScore1": 0, "PlayerScore10": 0, "PlayerScore11": 0, "PlayerScore2": 0, "PlayerScore3": 0, "PlayerScore4": 0, "PlayerScore5": 0, "PlayerScore6": 0, "PlayerScore7": 0, "PlayerScore8": 0, "PlayerScore9": 0, "allInPings": 0, "assistMePings": 3, "assists": 4, "baronKills": 0, "basicPings": 0, "bountyLevel": 1, "challenges": {"12AssistStreakCount": 0, "HealFromMapSources": 32.09097671508789, "InfernalScalePickup": 0, "SWARM_DefeatAatrox": 0, "SWARM_DefeatBriar": 0, "SWARM_DefeatMiniBosses": 0, "SWARM_EvolveWeapon": 0, "SWARM_Have3Passives": 0, "SWARM_KillEnemy": 0, "SWARM_PickupGold": 0, "SWARM_ReachLevel50": 0, "SWARM_Survive15Min": 0, "SWARM_WinWith5EvolvedWeapons": 0, "abilityUses": 265, "acesBefore15Minutes": 0, "alliedJungleMonsterKills": 0, "baronTakedowns": 0, "blastConeOppositeOpponentCount": 0, "bountyGold": 0, "buffsStolen": 5, "completeSupportQuestInTime": 0, "controlWardsPlaced": 0, "damagePerMinute": 346.5437058498327, "damageTakenOnTeamPercentage": 0.24927671169507, "dancedWithRiftHerald": 0, "deathsByEnemyChamps": 8, "dodgeSkillShotsSmallWindow": 0, "doubleAces": 0, "dragonTakedowns": 0, "earlyLaningPhaseGoldExpAdvantage": 0, "effectiveHealAndShielding": 0, "elderDragonKillsWithOpposingSoul": 0, "elderDragonMultikills": 0, "enemyChampionImmobilizations": 18, "enemyJungleMonsterKills": 0, "epicMonsterKillsNearEnemyJungler": 0, "epicMonsterKillsWithin30SecondsOfSpawn": 0, "epicMonsterSteals": 0, "epicMonsterStolenWithoutSmite": 0, "firstTurretKilled": 0, "fistBumpParticipation": 0, "flawlessAces": 0, "fullTeamTakedown": 0, "gameLength": 1646.3477353120002, "goldPerMinute": 295.54130596439035, "hadOpenNexus": 0, "immobilizeAndKillWithAlly": 3, "initialBuffCount": 2, "initialCrabCount": 0, "jungleCsBefore10Minutes": 36.000000059604645, "junglerKillsEarlyJungle": 0, "junglerTakedownsNearDamagedEpicMonster": 0, "kTurretsDestroyedBeforePlatesFall": 0, "kda": 0.625, "killAfterHiddenWithAlly": 0, "killParticipation": 0.4166666666666667, "killedChampTookFullTeamDamageSurvived": 0, "killingSprees": 0, "killsNearEnemyTurret": 1, "killsOnLanersEarlyJungleAsJungler": 0, "killsOnRecentlyHealedByAramPack": 0, "killsUnderOwnTurret": 0, "killsWithHelpFromEpicMonster": 0, "knockEnemyIntoTeamAndKill": 0, "landSkillShotsEarlyGame": 2, "laneMinionsFirst10Minutes": 1, "laningPhaseGoldExpAdvantage": 0, "legendaryCount": 0, "legendaryItemUsed": [3078, 6617, 3870, 3078, 6610], "lostAnInhibitor": 0, "maxCsAdvantageOnLaneOpponent": 8, "maxKillDeficit": 0, "maxLevelLeadLaneOpponent": 1, "mejaisFullStackInTime": 0, "moreEnemyJungleThanOpponent": 0, "multiKillOneSpell": 0, "multiTurretRiftHeraldCount": 0, "multikills": 0, "multikillsAfterAggressiveFlash": 0, "outerTurretExecutesBefore10Minutes": 0, "outnumberedKills": 0, "outnumberedNexusKill": 0, "perfectDragonSoulsTaken": 0, "perfectGame": 0, "pickKillWithAlly": 4, "playedChampSelectPosition": 1, "poroExplosions": 0, "quickCleanse": 0, "quickFirstTurret": 0, "quickSoloKills": 0, "riftHeraldTakedowns": 0, "saveAllyFromDeath": 0, "scuttleCrabKills": 0, "skillshotsDodged": 24, "skillshotsHit": 16, "snowballsHit": 0, "soloBaronKills": 0, "soloKills": 1, "stealthWardsPlaced": 7, "survivedSingleDigitHpCount": 0, "survivedThreeImmobilizesInFight": 2, "takedownOnFirstTurret": 0, "takedowns": 5, "takedownsAfterGainingLevelAdvantage": 0, "takedownsBeforeJungleMinionSpawn": 0, "takedownsFirstXMinutes": 3, "takedownsInAlcove": 0, "takedownsInEnemyFountain": 0, "teamBaronKills": 0, "teamDamagePercentage": 0.14365463861432531, "teamElderDragonKills": 0, "teamRiftHeraldKills": 0, "tookLargeDamageSurvived": 0, "turretPlatesTaken": 0, "turretTakedowns": 1, "turretsTakenWithRiftHerald": 0, "twentyMinionsIn3SecondsCount": 0, "twoWardsOneSweeperCount": 0, "unseenRecalls": 0, "visionScoreAdvantageLaneOpponent": -0.09694719314575195, "visionScorePerMinute": 0.4119500916401608, "voidMonsterKill": 1, "wardTakedowns": 0, "wardTakedownsBefore20M": 0, "wardsGuarded": 1}, "champExperience": 9572, "champLevel": 12, "championId": 234, "championName": "Viego", "championTransform": 0, "commandPings": 0, "consumablesPurchased": 0, "damageDealtToBuildings": 1991, "damageDealtToObjectives": 4721, "damageDealtToTurrets": 1991, "damageSelfMitigated": 13209, "dangerPings": 0, "deaths": 8, "detectorWardsPlaced": 0, "doubleKills": 0, "dragonKills": 0, "eligibleForProgression": true, "enemyMissingPings": 1, "enemyVisionPings": 0, "firstBloodAssist": false, "firstBloodKill": false, "firstTowerAssist": false, "firstTowerKill": false, "gameEndedInEarlySurrender": false, "gameEndedInSurrender": false, "getBackPings": 0, "goldEarned": 8109, "goldSpent": 7183, "holdPings": 0, "individualPosition": "JUNGLE", "inhibitorKills": 0, "inhibitorTakedowns": 0, "inhibitorsLost": 2, "item0": 3078, "item1": 1001, "item2": 6610, "item3": 0, "item4": 0, "item5": 0, "item6": 3340, "itemsPurchased": 11, "killingSprees": 0, "kills": 1, "lane": "JUNGLE", "largestCriticalStrike": 0, "largestKillingSpree": 0, "largestMultiKill": 1, "longestTimeSpentLiving": 381, "magicDamageDealt": 3971, "magicDamageDealtToChampions": 721, "magicDamageTaken": 13454, "missions": {"playerScore0": 0, "playerScore1": 0, "playerScore2": 0, "playerScore3": 0, "playerScore4": 0, "playerScore5": 0, "playerScore6": 0, "playerScore7": 0, "playerScore8": 0, "playerScore9": 0, "playerScore10": 0, "playerScore11": 0}, "needVisionPings": 1, "neutralMinionsKilled": 74, "nexusKills": 0, "nexusLost": 1, "nexusTakedowns": 0, "objectivesStolen": 0, "objectivesStolenAssists": 0, "onMyWayPings": 4, "participantId": 7, "pentaKills": 0, "perks": {"statPerks": {"defense": 5001, "flex": 5008, "offense": 5005}, "styles": [{"description": "primaryStyle", "selections": [{"perk": 8010, "var1": 152, "var2": 0, "var3": 0}, {"perk": 9111, "var1": 199, "var2": 100, "var3": 0}, {"perk": 9104, "var1": 19, "var2": 50, "var3": 0}, {"perk": 8014, "var1": 214, "var2": 0, "var3": 0}], "style": 8000}, {"description": "subStyle", "selections": [{"perk": 8143, "var1": 704, "var2": 0, "var3": 0}, {"perk": 8135, "var1": 210, "var2": 3, "var3": 0}], "style": 8100}]}, "physicalDamageDealt": 79218, "physicalDamageDealtToChampions": 7896, "physicalDamageTaken": 13425, "placement": 0, "playerAugment1": 0, "playerAugment2": 0, "playerAugment3": 0, "playerAugment4": 0, "playerAugment5": 0, "playerAugment6": 0, "playerSubteamId": 0, "profileIcon": 907, "pushPings": 0, "puuid": "HTqP5dug7zi1i0lGtmExmHZNmhpIgHNRDsMS1h5NE74E2jrzER-GzGx7n4KPD_eqFXN33OnkrKrfiQ", "quadraKills": 0, "retreatPings": 1, "riotIdGameName": "reazhy1", "riotIdTagline": "7074", "role": "NONE", "sightWardsBoughtInGame": 0, "spell1Casts": 137, "spell2Casts": 78, "spell3Casts": 45, "spell4Casts": 5, "subteamPlacement": 0, "summoner1Casts": 10, "summoner1Id": 11, "summoner2Casts": 4, "summoner2Id": 4, "summonerId": "YCLZxhNts5sTdcA92s5ngUzIqRA4T1uwqDkDc5_Tbj7g2uoYku-5BKiu3A", "summonerLevel": 70, "summonerName": "b675d94c221a", "teamEarlySurrendered": false, "teamId": 200, "teamPosition": "JUNGLE", "timeCCingOthers": 16, "timePlayed": 1646, "totalAllyJungleMinionsKilled": 0, "totalDamageDealt": 115731, "totalDamageDealtToChampions": 9508, "totalDamageShieldedOnTeammates": 0, "totalDamageTaken": 27528, "totalEnemyJungleMinionsKilled": 0, "totalHeal": 9204, "totalHealsOnTeammates": 0, "totalMinionsKilled": 39, "totalTimeCCDealt": 115, "totalTimeSpentDead": 182, "totalUnitsHealed": 1, "tripleKills": 0, "trueDamageDealt": 32542, "trueDamageDealtToChampions": 890, "trueDamageTaken": 647, "turretKills": 1, "turretTakedowns": 1, "turretsLost": 9, "unrealKills": 0, "visionClearedPings": 0, "visionScore": 11, "visionWardsBoughtInGame": 0, "wardsKilled": 0, "wardsPlaced": 7, "win": false}, {"PlayerScore0": 0, "PlayerScore1": 0, "PlayerScore10": 0, "PlayerScore11": 0, "PlayerScore2": 0, "PlayerScore3": 0, "PlayerScore4": 0, "PlayerScore5": 0, "PlayerScore6": 0, "PlayerScore7": 0, "PlayerScore8": 0, "PlayerScore9": 0, "allInPings": 0, "assistMePings": 4, "assists": 1, "baronKills": 0, "basicPings": 0, "bountyLevel": 5, "challenges": {"12AssistStreakCount": 0, "HealFromMapSources": 44, "InfernalScalePickup": 0, "SWARM_DefeatAatrox": 0, "SWARM_DefeatBriar": 0, "SWARM_DefeatMiniBosses": 0, "SWARM_EvolveWeapon": 0, "SWARM_Have3Passives": 0, "SWARM_KillEnemy": 0, "SWARM_PickupGold": 0, "SWARM_ReachLevel50": 0, "SWARM_Survive15Min": 0, "SWARM_WinWith5EvolvedWeapons": 0, "abilityUses": 283, "acesBefore15Minutes": 0, "alliedJungleMonsterKills": 0, "baronTakedowns": 0, "blastConeOppositeOpponentCount": 0, "bountyGold": 0, "buffsStolen": 0, "completeSupportQuestInTime": 0, "controlWardTimeCoverageInRiverOrEnemyHalf": 0.3685173736088157, "controlWardsPlaced": 1, "damagePerMinute": 548.5193287652331, "damageTakenOnTeamPercentage": 0.1560397763600679, "dancedWithRiftHerald": 0, "deathsByEnemyChamps": 6, "dodgeSkillShotsSmallWindow": 0, "doubleAces": 0, "dragonTakedowns": 0, "earlyLaningPhaseGoldExpAdvantage": 0, "effectiveHealAndShielding": 0, "elderDragonKillsWithOpposingSoul": 0, "elderDragonMultikills": 0, "enemyChampionImmobilizations": 83, "enemyJungleMonsterKills": 0, "epicMonsterKillsNearEnemyJungler": 0, "epicMonsterKillsWithin30SecondsOfSpawn": 0, "epicMonsterSteals": 0, "epicMonsterStolenWithoutSmite": 0, "firstTurretKilled": 0, "fistBumpParticipation": 0, "flawlessAces": 0, "fullTeamTakedown": 0, "gameLength": 1646.3477353120002, "getTakedownsInAllLanesEarlyJungleAsLaner": 0, "goldPerMinute": 298.02628087263764, "hadOpenNexus": 0, "immobilizeAndKillWithAlly": 1, "initialBuffCount": 0, "initialCrabCount": 0, "jungleCsBefore10Minutes": 0, "junglerTakedownsNearDamagedEpicMonster": 1, "kTurretsDestroyedBeforePlatesFall": 0, "kda": 1, "killAfterHiddenWithAlly": 0, "killParticipation": 0.5, "killedChampTookFullTeamDamageSurvived": 0, "killingSprees": 0, "killsNearEnemyTurret": 1, "killsOnOtherLanesEarlyJungleAsLaner": 0, "killsOnRecentlyHealedByAramPack": 0, "killsUnderOwnTurret": 1, "killsWithHelpFromEpicMonster": 1, "knockEnemyIntoTeamAndKill": 2, "landSkillShotsEarlyGame": 2, "laneMinionsFirst10Minutes": 55, "laningPhaseGoldExpAdvantage": 0, "legendaryCount": 0, "legendaryItemUsed": [3102, 3003, 3040], "lostAnInhibitor": 0, "maxCsAdvantageOnLaneOpponent": 27, "maxKillDeficit": 0, "maxLevelLeadLaneOpponent": 1, "mejaisFullStackInTime": 0, "moreEnemyJungleThanOpponent": 0, "multiKillOneSpell": 0, "multiTurretRiftHeraldCount": 0, "multikills": 0, "multikillsAfterAggressiveFlash": 0, "outerTurretExecutesBefore10Minutes": 0, "outnumberedKills": 3, "outnumberedNexusKill": 0, "perfectDragonSoulsTaken": 0, "perfectGame": 0, "pickKillWithAlly": 5, "playedChampSelectPosition": 1, "poroExplosions": 0, "quickCleanse": 0, "quickFirstTurret": 0, "quickSoloKills": 0, "riftHeraldTakedowns": 0, "saveAllyFromDeath": 0, "scuttleCrabKills": 0, "skillshotsDodged": 27, "skillshotsHit": 13, "snowballsHit": 0, "soloBaronKills": 0, "soloKills": 1, "stealthWardsPlaced": 6, "survivedSingleDigitHpCount": 0, "survivedThreeImmobilizesInFight": 3, "takedownOnFirstTurret": 0, "takedowns": 6, "takedownsAfterGainingLevelAdvantage": 0, "takedownsBeforeJungleMinionSpawn": 0, "takedownsFirstXMinutes": 5, "takedownsInAlcove": 0, "takedownsInEnemyFountain": 0, "teamBaronKills": 0, "teamDamagePercentage": 0.22738068710123105, "teamElderDragonKills": 0, "teamRiftHeraldKills": 0, "tookLargeDamageSurvived": 0, "turretPlatesTaken": 0, "turretTakedowns": 0, "turretsTakenWithRiftHerald": 0, "twentyMinionsIn3SecondsCount": 0, "twoWardsOneSweeperCount": 0, "unseenRecalls": 0, "visionScoreAdvantageLaneOpponent": -0.5247077941894531, "visionScorePerMinute": 0.4035730619213229, "voidMonsterKill": 0, "wardTakedowns": 1, "wardTakedownsBefore20M": 1, "wardsGuarded": 0}, "champExperience": 10358, "champLevel": 13, "championId": 134, "championName": "Syndra", "championTransform": 0, "commandPings": 0, "consumablesPurchased": 4, "damageDealtToBuildings": 361, "damageDealtToObjectives": 572, "damageDealtToTurrets": 361, "damageSelfMitigated": 9249, "dangerPings": 0, "deaths": 6, "detectorWardsPlaced": 1, "doubleKills": 0, "dragonKills": 0, "eligibleForProgression": true, "enemyMissingPings": 13, "enemyVisionPings": 0, "firstBloodAssist": false, "firstBloodKill": false, "firstTowerAssist": false, "firstTowerKill": false, "gameEndedInEarlySurrender": false, "gameEndedInSurrender": false, "getBackPings": 0, "goldEarned": 8177, "goldSpent": 8450, "holdPings": 0, "individualPosition": "MIDDLE", "inhibitorKills": 0, "inhibitorTakedowns": 0, "inhibitorsLost": 2, "item0": 3102, "item1": 2055, "item2": 3040, "item3": 3020, "item4": 0, "item5": 0, "item6": 3363, "itemsPurchased": 27, "killingSprees": 2, "kills": 5, "lane": "MIDDLE", "largestCriticalStrike": 0, "largestKillingSpree": 2, "largestMultiKill": 1, "longestTimeSpentLiving": 464, "magicDamageDealt": 83947, "magicDamageDealtToChampions": 13664, "magicDamageTaken": 7890, "missions": {"playerScore0": 0, "playerScore1": 0, "playerScore2": 0, "playerScore3": 0, "playerScore4": 0, "playerScore5": 0, "playerScore6": 0, "playerScore7": 0, "playerScore8": 0, "playerScore9": 0, "playerScore10": 0, "playerScore11": 0}, "needVisionPings": 0, "neutralMinionsKilled": 0, "nexusKills": 0, "nexusLost": 1, "nexusTakedowns": 0, "objectivesStolen": 0, "objectivesStolenAssists": 0, "onMyWayPings": 1, "participantId": 8, "pentaKills": 0, "perks": {"statPerks": {"defense": 5011, "flex": 5008, "offense": 5007}, "styles": [{"description": "primaryStyle", "selections": [{"perk": 8112, "var1": 873, "var2": 0, "var3": 0}, {"perk": 8139, "var1": 706, "var2": 0, "var3": 0}, {"perk": 8140, "var1": 6, "var2": 0, "var3": 0}, {"perk": 8106, "var1": 3, "var2": 21, "var3": 0}], "style": 8100}, {"description": "subStyle", "selections": [{"perk": 8237, "var1": 600, "var2": 0, "var3": 0}, {"perk": 8226, "var1": 250, "var2": 369, "var3": 0}], "style": 8200}]}, "physicalDamageDealt": 8631, "physicalDamageDealtToChampions": 1180, "physicalDamageTaken": 8255, "placement": 0, "playerAugment1": 0, "playerAugment2": 0, "playerAugment3": 0, "playerAugment4": 0, "playerAugment5": 0, "playerAugment6": 0, "playerSubteamId": 0, "profileIcon": 903, "pushPings": 0, "puuid": "9iX3byb9GA3veD_B7cEyB509TAE_y4AHTNoStg0-TPebVJ5Yyyqaa-fzgFnASU179PTWqkkcrAtpEg", "quadraKills": 0, "retreatPings": 1, "riotIdGameName": "WabiSabiScottie", "riotIdTagline": "WSS", "role": "SOLO", "sightWardsBoughtInGame": 0, "spell1Casts": 124, "spell2Casts": 112, "spell3Casts": 38, "spell4Casts": 9, "subteamPlacement": 0, "summoner1Casts": 4, "summoner1Id": 12, "summoner2Casts": 5, "summoner2Id": 4, "summonerId": "Vmo12ZE1CLoOy6WsFcjpdp9Akv88CjpmZoeKwGl6gGD1ghOncCDyjCu5LQ", "summonerLevel": 515, "summonerName": "HidingInUrJungle", "teamEarlySurrendered": false, "teamId": 200, "teamPosition": "MIDDLE", "timeCCingOthers": 29, "timePlayed": 1646, "totalAllyJungleMinionsKilled": 0, "totalDamageDealt": 94307, "totalDamageDealtToChampions": 15050, "totalDamageShieldedOnTeammates": 0, "totalDamageTaken": 17231, "totalEnemyJungleMinionsKilled": 0, "totalHeal": 1026, "totalHealsOnTeammates": 0, "totalMinionsKilled": 136, "totalTimeCCDealt": 506, "totalTimeSpentDead": 165, "totalUnitsHealed": 1, "tripleKills": 0, "trueDamageDealt": 1728, "trueDamageDealtToChampions": 205, "trueDamageTaken": 1086, "turretKills": 0, "turretTakedowns": 0, "turretsLost": 9, "unrealKills": 0, "visionClearedPings": 0, "visionScore": 11, "visionWardsBoughtInGame": 2, "wardsKilled": 1, "wardsPlaced": 8, "win": false}, {"PlayerScore0": 0, "PlayerScore1": 0, "PlayerScore10": 0, "PlayerScore11": 0, "PlayerScore2": 0, "PlayerScore3": 0, "PlayerScore4": 0, "PlayerScore5": 0, "PlayerScore6": 0, "PlayerScore7": 0, "PlayerScore8": 0, "PlayerScore9": 0, "allInPings": 0, "assistMePings": 0, "assists": 2, "baronKills": 0, "basicPings": 0, "bountyLevel": 2, "challenges": {"12AssistStreakCount": 0, "HealFromMapSources": 0, "InfernalScalePickup": 0, "SWARM_DefeatAatrox": 0, "SWARM_DefeatBriar": 0, "SWARM_DefeatMiniBosses": 0, "SWARM_EvolveWeapon": 0, "SWARM_Have3Passives": 0, "SWARM_KillEnemy": 0, "SWARM_PickupGold": 0, "SWARM_ReachLevel50": 0, "SWARM_Survive15Min": 0, "SWARM_WinWith5EvolvedWeapons": 0, "abilityUses": 75, "acesBefore15Minutes": 0, "alliedJungleMonsterKills": 0, "baronTakedowns": 0, "blastConeOppositeOpponentCount": 0, "bountyGold": 0, "buffsStolen": 0, "completeSupportQuestInTime": 0, "controlWardsPlaced": 0, "damagePerMinute": 420.93770889700124, "damageTakenOnTeamPercentage": 0.18194938249078024, "dancedWithRiftHerald": 0, "deathsByEnemyChamps": 9, "dodgeSkillShotsSmallWindow": 0, "doubleAces": 0, "dragonTakedowns": 0, "earlyLaningPhaseGoldExpAdvantage": 0, "effectiveHealAndShielding": 0, "elderDragonKillsWithOpposingSoul": 0, "elderDragonMultikills": 0, "enemyChampionImmobilizations": 3, "enemyJungleMonsterKills": 0, "epicMonsterKillsNearEnemyJungler": 0, "epicMonsterKillsWithin30SecondsOfSpawn": 0, "epicMonsterSteals": 0, "epicMonsterStolenWithoutSmite": 0, "firstTurretKilled": 0, "fistBumpParticipation": 0, "flawlessAces": 0, "fullTeamTakedown": 0, "gameLength": 1646.3477353120002, "getTakedownsInAllLanesEarlyJungleAsLaner": 0, "goldPerMinute": 283.5452392513747, "hadOpenNexus": 0, "immobilizeAndKillWithAlly": 0, "initialBuffCount": 0, "initialCrabCount": 0, "jungleCsBefore10Minutes": 0, "junglerTakedownsNearDamagedEpicMonster": 0, "kTurretsDestroyedBeforePlatesFall": 0, "kda": 0.4444444444444444, "killAfterHiddenWithAlly": 0, "killParticipation": 0.3333333333333333, "killedChampTookFullTeamDamageSurvived": 0, "killingSprees": 0, "killsNearEnemyTurret": 0, "killsOnOtherLanesEarlyJungleAsLaner": 0, "killsOnRecentlyHealedByAramPack": 0, "killsUnderOwnTurret": 0, "killsWithHelpFromEpicMonster": 0, "knockEnemyIntoTeamAndKill": 0, "landSkillShotsEarlyGame": 7, "laneMinionsFirst10Minutes": 59, "laningPhaseGoldExpAdvantage": 0, "legendaryCount": 0, "legendaryItemUsed": [3153, 3085], "lostAnInhibitor": 0, "maxCsAdvantageOnLaneOpponent": 30, "maxKillDeficit": 0, "maxLevelLeadLaneOpponent": 1, "mejaisFullStackInTime": 0, "moreEnemyJungleThanOpponent": 0, "multiKillOneSpell": 0, "multiTurretRiftHeraldCount": 0, "multikills": 0, "multikillsAfterAggressiveFlash": 0, "outerTurretExecutesBefore10Minutes": 0, "outnumberedKills": 1, "outnumberedNexusKill": 0, "perfectDragonSoulsTaken": 0, "perfectGame": 0, "pickKillWithAlly": 4, "playedChampSelectPosition": 1, "poroExplosions": 0, "quickCleanse": 0, "quickFirstTurret": 0, "quickSoloKills": 0, "riftHeraldTakedowns": 0, "saveAllyFromDeath": 0, "scuttleCrabKills": 1, "skillshotsDodged": 10, "skillshotsHit": 20, "snowballsHit": 0, "soloBaronKills": 0, "soloKills": 0, "stealthWardsPlaced": 3, "survivedSingleDigitHpCount": 0, "survivedThreeImmobilizesInFight": 0, "takedownOnFirstTurret": 0, "takedowns": 4, "takedownsAfterGainingLevelAdvantage": 0, "takedownsBeforeJungleMinionSpawn": 0, "takedownsFirstXMinutes": 4, "takedownsInAlcove": 0, "takedownsInEnemyFountain": 0, "teamBaronKills": 0, "teamDamagePercentage": 0.174493587475353, "teamElderDragonKills": 0, "teamRiftHeraldKills": 0, "tookLargeDamageSurvived": 0, "turretPlatesTaken": 2, "turretTakedowns": 0, "turretsTakenWithRiftHerald": 0, "twentyMinionsIn3SecondsCount": 0, "twoWardsOneSweeperCount": 0, "unseenRecalls": 0, "visionScoreAdvantageLaneOpponent": 0.08610546588897705, "visionScorePerMinute": 0.5678030431981044, "voidMonsterKill": 0, "wardTakedowns": 1, "wardTakedownsBefore20M": 1, "wardsGuarded": 0}, "champExperience": 9706, "champLevel": 12, "championId": 22, "championName": "Ashe", "championTransform": 0, "commandPings": 0, "consumablesPurchased": 1, "damageDealtToBuildings": 807, "damageDealtToObjectives": 807, "damageDealtToTurrets": 807, "damageSelfMitigated": 9581, "dangerPings": 0, "deaths": 9, "detectorWardsPlaced": 0, "doubleKills": 0, "dragonKills": 0, "eligibleForProgression": true, "enemyMissingPings": 0, "enemyVisionPings": 0, "firstBloodAssist": false, "firstBloodKill": true, "firstTowerAssist": false, "firstTowerKill": false, "gameEndedInEarlySurrender": false, "gameEndedInSurrender": false, "getBackPings": 0, "goldEarned": 7780, "goldSpent": 7450, "holdPings": 0, "individualPosition": "BOTTOM", "inhibitorKills": 0, "inhibitorTakedowns": 0, "inhibitorsLost": 2, "item0": 1055, "item1": 3153, "item2": 3006, "item3": 3085, "item4": 0, "item5": 0, "item6": 3340, "itemsPurchased": 13, "killingSprees": 0, "kills": 2, "lane": "BOTTOM", "largestCriticalStrike": 169, "largestKillingSpree": 0, "largestMultiKill": 1, "longestTimeSpentLiving": 397, "magicDamageDealt": 371, "magicDamageDealtToChampions": 371, "magicDamageTaken": 5701, "missions": {"playerScore0": 0, "playerScore1": 0, "playerScore2": 0, "playerScore3": 0, "playerScore4": 0, "playerScore5": 0, "playerScore6": 0, "playerScore7": 0, "playerScore8": 0, "playerScore9": 0, "playerScore10": 0, "playerScore11": 0}, "needVisionPings": 0, "neutralMinionsKilled": 4, "nexusKills": 0, "nexusLost": 1, "nexusTakedowns": 0, "objectivesStolen": 0, "objectivesStolenAssists": 0, "onMyWayPings": 0, "participantId": 9, "pentaKills": 0, "perks": {"statPerks": {"defense": 5001, "flex": 5008, "offense": 5005}, "styles": [{"description": "primaryStyle", "selections": [{"perk": 8005, "var1": 753, "var2": 753, "var3": 0}, {"perk": 9111, "var1": 174, "var2": 80, "var3": 0}, {"perk": 9104, "var1": 0, "var2": 0, "var3": 0}, {"perk": 8014, "var1": 237, "var2": 0, "var3": 0}], "style": 8000}, {"description": "subStyle", "selections": [{"perk": 8126, "var1": 503, "var2": 0, "var3": 0}, {"perk": 8106, "var1": 2, "var2": 16, "var3": 0}], "style": 8100}]}, "physicalDamageDealt": 71902, "physicalDamageDealtToChampions": 10675, "physicalDamageTaken": 13863, "placement": 0, "playerAugment1": 0, "playerAugment2": 0, "playerAugment3": 0, "playerAugment4": 0, "playerAugment5": 0, "playerAugment6": 0, "playerSubteamId": 0, "profileIcon": 6491, "pushPings": 0, "puuid": "24ZsDGG_0A6h2-a8o3O-u6_vbsRtLA0XPhYDXTInzIxfdOI8TIxt1KjTHjLahbJ-QeZxAoZlORO2xg", "quadraKills": 0, "retreatPings": 0, "riotIdGameName": "brazillian beach", "riotIdTagline": "069", "role": "CARRY", "sightWardsBoughtInGame": 0, "spell1Casts": 20, "spell2Casts": 37, "spell3Casts": 11, "spell4Casts": 7, "subteamPlacement": 0, "summoner1Casts": 4, "summoner1Id": 21, "summoner2Casts": 3, "summoner2Id": 4, "summonerId": "YRBp1uoryN-CbwqvKW6IBuJ5RoXWNe47u3aPsblOveI5DrOUSsHWonXVWQ", "summonerLevel": 32, "summonerName": "", "teamEarlySurrendered": false, "teamId": 200, "teamPosition": "BOTTOM", "timeCCingOthers": 31, "timePlayed": 1646, "totalAllyJungleMinionsKilled": 0, "totalDamageDealt": 77048, "totalDamageDealtToChampions": 11550, "totalDamageShieldedOnTeammates": 0, "totalDamageTaken": 20093, "totalEnemyJungleMinionsKilled": 0, "totalHeal": 3901, "totalHealsOnTeammates": 0, "totalMinionsKilled": 132, "totalTimeCCDealt": 514, "totalTimeSpentDead": 191, "totalUnitsHealed": 1, "tripleKills": 0, "trueDamageDealt": 4774, "trueDamageDealtToChampions": 503, "trueDamageTaken": 528, "turretKills": 0, "turretTakedowns": 0, "turretsLost": 9, "unrealKills": 0, "visionClearedPings": 0, "visionScore": 15, "visionWardsBoughtInGame": 0, "wardsKilled": 1, "wardsPlaced": 3, "win": false}, {"PlayerScore0": 0, "PlayerScore1": 0, "PlayerScore10": 0, "PlayerScore11": 0, "PlayerScore2": 0, "PlayerScore3": 0, "PlayerScore4": 0, "PlayerScore5": 0, "PlayerScore6": 0, "PlayerScore7": 0, "PlayerScore8": 0, "PlayerScore9": 0, "allInPings": 0, "assistMePings": 3, "assists": 2, "baronKills": 0, "basicPings": 0, "bountyLevel": 4, "challenges": {"12AssistStreakCount": 0, "HealFromMapSources": 0, "InfernalScalePickup": 0, "SWARM_DefeatAatrox": 0, "SWARM_DefeatBriar": 0, "SWARM_DefeatMiniBosses": 0, "SWARM_EvolveWeapon": 0, "SWARM_Have3Passives": 0, "SWARM_KillEnemy": 0, "SWARM_PickupGold": 0, "SWARM_ReachLevel50": 0, "SWARM_Survive15Min": 0, "SWARM_WinWith5EvolvedWeapons": 0, "abilityUses": 266, "acesBefore15Minutes": 0, "alliedJungleMonsterKills": 0, "baronTakedowns": 0, "blastConeOppositeOpponentCount": 0, "bountyGold": 1006.2347869873047, "buffsStolen": 0, "completeSupportQuestInTime": 0, "controlWardsPlaced": 0, "damagePerMinute": 637.4395907093217, "damageTakenOnTeamPercentage": 0.19060438220665227, "dancedWithRiftHerald": 0, "deathsByEnemyChamps": 10, "dodgeSkillShotsSmallWindow": 0, "doubleAces": 0, "dragonTakedowns": 0, "earlyLaningPhaseGoldExpAdvantage": 0, "effectiveHealAndShielding": 0, "elderDragonKillsWithOpposingSoul": 0, "elderDragonMultikills": 0, "enemyChampionImmobilizations": 27, "enemyJungleMonsterKills": 0, "epicMonsterKillsNearEnemyJungler": 0, "epicMonsterKillsWithin30SecondsOfSpawn": 0, "epicMonsterSteals": 0, "epicMonsterStolenWithoutSmite": 0, "firstTurretKilled": 0, "fistBumpParticipation": 0, "flawlessAces": 0, "fullTeamTakedown": 0, "gameLength": 1646.3477353120002, "getTakedownsInAllLanesEarlyJungleAsLaner": 0, "goldPerMinute": 351.1307413264654, "hadOpenNexus": 0, "highestCrowdControlScore": 1, "immobilizeAndKillWithAlly": 1, "initialBuffCount": 0, "initialCrabCount": 0, "jungleCsBefore10Minutes": 0, "junglerTakedownsNearDamagedEpicMonster": 0, "kTurretsDestroyedBeforePlatesFall": 0, "kda": 0.6, "killAfterHiddenWithAlly": 0, "killParticipation": 0.5, "killedChampTookFullTeamDamageSurvived": 0, "killingSprees": 0, "killsNearEnemyTurret": 0, "killsOnOtherLanesEarlyJungleAsLaner": 0, "killsOnRecentlyHealedByAramPack": 0, "killsUnderOwnTurret": 2, "killsWithHelpFromEpicMonster": 0, "knockEnemyIntoTeamAndKill": 0, "landSkillShotsEarlyGame": 3, "laneMinionsFirst10Minutes": 4, "laningPhaseGoldExpAdvantage": 0, "legendaryCount": 0, "legendaryItemUsed": [2503, 3871, 3165], "lostAnInhibitor": 0, "maxCsAdvantageOnLaneOpponent": 34, "maxKillDeficit": 0, "maxLevelLeadLaneOpponent": 1, "mejaisFullStackInTime": 0, "moreEnemyJungleThanOpponent": 0, "multiKillOneSpell": 0, "multiTurretRiftHeraldCount": 0, "multikills": 0, "multikillsAfterAggressiveFlash": 0, "outerTurretExecutesBefore10Minutes": 0, "outnumberedKills": 0, "outnumberedNexusKill": 0, "perfectDragonSoulsTaken": 0, "perfectGame": 0, "pickKillWithAlly": 5, "playedChampSelectPosition": 1, "poroExplosions": 0, "quickCleanse": 0, "quickFirstTurret": 0, "quickSoloKills": 0, "riftHeraldTakedowns": 0, "saveAllyFromDeath": 0, "scuttleCrabKills": 0, "skillshotsDodged": 15, "skillshotsHit": 21, "snowballsHit": 0, "soloBaronKills": 0, "soloKills": 1, "stealthWardsPlaced": 12, "survivedSingleDigitHpCount": 0, "survivedThreeImmobilizesInFight": 0, "takedownOnFirstTurret": 0, "takedowns": 6, "takedownsAfterGainingLevelAdvantage": 0, "takedownsBeforeJungleMinionSpawn": 0, "takedownsFirstXMinutes": 4, "takedownsInAlcove": 0, "takedownsInEnemyFountain": 0, "teamBaronKills": 0, "teamDamagePercentage": 0.2642412847096737, "teamElderDragonKills": 0, "teamRiftHeraldKills": 0, "tookLargeDamageSurvived": 0, "turretPlatesTaken": 1, "turretTakedowns": 2, "turretsTakenWithRiftHerald": 0, "twentyMinionsIn3SecondsCount": 0, "twoWardsOneSweeperCount": 0, "unseenRecalls": 0, "visionScoreAdvantageLaneOpponent": -0.4726446270942688, "visionScorePerMinute": 0.7795978940328103, "voidMonsterKill": 0, "wardTakedowns": 1, "wardTakedownsBefore20M": 1, "wardsGuarded": 0}, "champExperience": 8956, "champLevel": 12, "championId": 143, "championName": "Zyra", "championTransform": 0, "commandPings": 2, "consumablesPurchased": 0, "damageDealtToBuildings": 3270, "damageDealtToObjectives": 4265, "damageDealtToTurrets": 3270, "damageSelfMitigated": 7361, "dangerPings": 0, "deaths": 10, "detectorWardsPlaced": 0, "doubleKills": 0, "dragonKills": 0, "eligibleForProgression": true, "enemyMissingPings": 1, "enemyVisionPings": 0, "firstBloodAssist": true, "firstBloodKill": false, "firstTowerAssist": false, "firstTowerKill": false, "gameEndedInEarlySurrender": false, "gameEndedInSurrender": false, "getBackPings": 0, "goldEarned": 9634, "goldSpent": 8250, "holdPings": 0, "individualPosition": "UTILITY", "inhibitorKills": 0, "inhibitorTakedowns": 0, "inhibitorsLost": 2, "item0": 3871, "item1": 3070, "item2": 2503, "item3": 3165, "item4": 1026, "item5": 3108, "item6": 3340, "itemsPurchased": 16, "killingSprees": 1, "kills": 4, "lane": "BOTTOM", "largestCriticalStrike": 0, "largestKillingSpree": 2, "largestMultiKill": 1, "longestTimeSpentLiving": 384, "magicDamageDealt": 80903, "magicDamageDealtToChampions": 15272, "magicDamageTaken": 12236, "missions": {"playerScore0": 0, "playerScore1": 0, "playerScore2": 0, "playerScore3": 0, "playerScore4": 0, "playerScore5": 0, "playerScore6": 0, "playerScore7": 0, "playerScore8": 0, "playerScore9": 0, "playerScore10": 0, "playerScore11": 0}, "needVisionPings": 0, "neutralMinionsKilled": 0, "nexusKills": 0, "nexusLost": 1, "nexusTakedowns": 0, "objectivesStolen": 0, "objectivesStolenAssists": 0, "onMyWayPings": 2, "participantId": 10, "pentaKills": 0, "perks": {"statPerks": {"defense": 5001, "flex": 5008, "offense": 5008}, "styles": [{"description": "primaryStyle", "selections": [{"perk": 8229, "var1": 1606, "var2": 0, "var3": 0}, {"perk": 8226, "var1": 250, "var2": 564, "var3": 0}, {"perk": 8210, "var1": 0, "var2": 0, "var3": 0}, {"perk": 8237, "var1": 526, "var2": 0, "var3": 0}], "style": 8200}, {"description": "subStyle", "selections": [{"perk": 8139, "var1": 877, "var2": 0, "var3": 0}, {"perk": 8105, "var1": 16, "var2": 2, "var3": 0}], "style": 8100}]}, "physicalDamageDealt": 7520, "physicalDamageDealtToChampions": 1202, "physicalDamageTaken": 7717, "placement": 0, "playerAugment1": 0, "playerAugment2": 0, "playerAugment3": 0, "playerAugment4": 0, "playerAugment5": 0, "playerAugment6": 0, "playerSubteamId": 0, "profileIcon": 6725, "pushPings": 0, "puuid": "DMNamjYDDtuA5lsPIn2jB610zoD4He7IhKBQ-UqLdGgqO_w5lhHyv7BHJfd4Kn5sHWL2FHalRYaqIw", "quadraKills": 0, "retreatPings": 0, "riotIdGameName": "Kimber3", "riotIdTagline": "NA1", "role": "SUPPORT", "sightWardsBoughtInGame": 0, "spell1Casts": 78, "spell2Casts": 102, "spell3Casts": 73, "spell4Casts": 13, "subteamPlacement": 0, "summoner1Casts": 5, "summoner1Id": 4, "summoner2Casts": 7, "summoner2Id": 14, "summonerId": "EVzIONdB4ES1XQcUXEm2Pjca3BTpoZkjLcDgVt8RYboSaBI2", "summonerLevel": 664, "summonerName": "Kimber3", "teamEarlySurrendered": false, "teamId": 200, "teamPosition": "UTILITY", "timeCCingOthers": 43, "timePlayed": 1646, "totalAllyJungleMinionsKilled": 0, "totalDamageDealt": 89889, "totalDamageDealtToChampions": 17490, "totalDamageShieldedOnTeammates": 0, "totalDamageTaken": 21048, "totalEnemyJungleMinionsKilled": 0, "totalHeal": 875, "totalHealsOnTeammates": 0, "totalMinionsKilled": 78, "totalTimeCCDealt": 350, "totalTimeSpentDead": 271, "totalUnitsHealed": 1, "tripleKills": 0, "trueDamageDealt": 1466, "trueDamageDealtToChampions": 1015, "trueDamageTaken": 1095, "turretKills": 2, "turretTakedowns": 2, "turretsLost": 9, "unrealKills": 0, "visionClearedPings": 0, "visionScore": 21, "visionWardsBoughtInGame": 0, "wardsKilled": 1, "wardsPlaced": 12, "win": false}], "platformId": "NA1", "queueId": 420, "teams": [{"bans": [{"championId": 103, "pickTurn": 1}, {"championId": 82, "pickTurn": 2}, {"championId": 50, "pickTurn": 3}, {"championId": 99, "pickTurn": 4}, {"championId": 9, "pickTurn": 5}], "objectives": {"atakhan": {"first": true, "kills": 1}, "baron": {"first": true, "kills": 1}, "champion": {"first": false, "kills": 35}, "dragon": {"first": true, "kills": 4}, "horde": {"first": true, "kills": 2}, "inhibitor": {"first": true, "kills": 2}, "riftHerald": {"first": true, "kills": 1}, "tower": {"first": true, "kills": 9}}, "teamId": 100, "win": true}, {"bans": [{"championId": 19, "pickTurn": 6}, {"championId": 90, "pickTurn": 7}, {"championId": 203, "pickTurn": 8}, {"championId": 777, "pickTurn": 9}, {"championId": -1, "pickTurn": 10}], "objectives": {"baron": {"first": false, "kills": 0}, "champion": {"first": true, "kills": 12}, "dragon": {"first": false, "kills": 0}, "horde": {"first": false, "kills": 1}, "inhibitor": {"first": false, "kills": 0}, "riftHerald": {"first": false, "kills": 0}, "tower": {"first": false, "kills": 4}}, "teamId": 200, "win": false}], "tournamentCode": ""}}